{
  "id": "1766515561801-c6ara0akv",
  "subject": "PL-300",
  "generatedAt": "2025-12-23T18:46:01.801Z",
  "fullDocument": "================================================================================\nVISUAL MASTER CHART: Microsoft Learn - PL-300: Microsoft Power BI Data Analyst Exam Skills Measured (Updated December 2024)\nGenerated: 2025-12-23T18:41:11.237Z\n================================================================================\n\nDOMAIN ANALYSIS\n---------------\nDomain: Business Intelligence & Data Analytics\nProfessional Role: Power BI Data Analyst\nLifecycle: PREPARE → MODEL → DELIVER\n\nSource Verification: Microsoft Learn - PL-300: Microsoft Power BI Data Analyst Exam Skills Measured (Updated December 2024)\n\nRecent Updates:\n  • Enhanced emphasis on Power BI Service workspace management and deployment pipelines (added Q4 2024)\n  • Expanded coverage of DirectQuery optimization and hybrid table configurations introduced with Fabric integration (added Q3 2024)\n  • New focus on Copilot for Power BI features including natural language query assistance and AI-generated insights (added Q4 2024)\n\nNumerical Limits:\n  • Power BI Pro: 10 GB dataset size limit per workspace\n  • Power BI Premium Per User: 100 GB dataset size limit\n  • DirectQuery: 1 million row practical limit for optimal performance\n  • Refresh frequency (Pro): Maximum 8 refreshes per day\n  • Refresh frequency (Premium): Maximum 48 refreshes per day\n  • Dashboard tiles: Maximum 200 tiles per dashboard\n  • Report pages: Maximum 50 pages per report file\n  • Row-level security roles: Maximum 100 roles per dataset\n\nCore Concepts Identified: 50\n  1. Power BI Service Workspace Management\n  2. Power BI Desktop Environment\n  3. Data Source Connectivity\n  4. Power Query Editor (M Language)\n  5. Data Transformation and Cleaning\n  6. Import vs DirectQuery vs Live Connection Storage Modes\n  7. Composite Models and Hybrid Tables\n  8. Data Refresh Configuration\n  9. Star Schema Design\n  10. Table Relationships and Cardinality\n  11. DAX Calculated Columns\n  12. DAX Measures and Implicit Measures\n  13. DAX Iterator Functions (SUMX, AVERAGEX)\n  14. DAX Filter Context and Row Context\n  15. DAX Time Intelligence Functions\n  16. DAX Variables and Query Performance\n  17. Row-Level Security (RLS)\n  18. Object-Level Security (OLS)\n  19. Data Categorization and Hierarchies\n  20. Visual Selection and Use Cases\n  21. Custom Visuals from AppSource\n  22. Report Layout and Page Design\n  23. Slicers and Cross-Filtering Behavior\n  24. Drillthrough and Drill-down Navigation\n  25. Bookmarks and Selection Pane\n  26. Buttons and Action Configuration\n  27. Tooltips (Standard and Report Page)\n  28. Conditional Formatting\n  29. Dashboard Creation from Reports\n  30. Dashboard Tiles and Q&A\n  31. Mobile Layout Optimization\n  32. Paginated Reports (SSRS-style)\n  33. Power BI Apps for Distribution\n  34. Workspace Roles and Permissions\n  35. Deployment Pipelines (Dev/Test/Prod)\n  36. Dataset Endorsement (Certified/Promoted)\n  37. Gateway Configuration for On-Premises Data\n  38. Dataflows for Self-Service ETL\n  39. Incremental Refresh Policy\n  40. Query Folding Optimization\n  41. Performance Analyzer Tool\n  42. DAX Studio for Query Optimization\n  43. Lineage View and Impact Analysis\n  44. Sensitivity Labels and Data Protection\n  45. Usage Metrics and Report Analytics\n  46. Alerts and Subscriptions\n  47. Export Options (PDF, PowerPoint, Excel)\n  48. Embed Reports in Teams/SharePoint\n  49. Goals and Metrics Feature\n  50. Copilot for Power BI Natural Language Queries\n\n================================================================================\nCONCEPT DEPENDENCY GRAPH & DECISION FRAMEWORKS\n================================================================================\n\n# STEP 3.5: DECISION FRAMEWORK TREES\n\n## Decision Tree 1: Storage Mode Selection (Import vs DirectQuery vs Live Connection vs Composite)\n\n**Decision Question:** \"Which storage mode unlocks the capabilities I need for this dataset?\"\n\n```\nSTART: Evaluating Data Storage Strategy\n│\n├─── Question 1: What is your primary performance optimization goal?\n│    │\n│    ├─── \"Fastest query response for end users\" \n│    │    │\n│    │    └─── Question 2: Is the dataset under 10 GB (Pro) or 100 GB (Premium Per User)?\n│    │         │\n│    │         ├─── YES → **Choose IMPORT MODE**\n│    │         │         ✓ Unlocks: Sub-second query performance through in-memory analytics\n│    │         │         ✓ Enables: All DAX capabilities including complex calculations\n│    │         │         ✓ Best suited for: Dashboards requiring instant responsiveness\n│    │         │         ✓ Optimized for: Aggregated historical data and time intelligence\n│    │         │         → Configure scheduled refresh (8x daily Pro, 48x daily Premium)\n│    │         │\n│    │         └─── NO → Consider **INCREMENTAL REFRESH** with Import\n│    │                   ✓ Unlocks: Import performance for large datasets by refreshing only recent data\n│    │                   ✓ Enables: Historical data retention while managing refresh windows\n│    │                   ✓ Best suited for: Datasets 10GB+ with time-based partitioning\n│    │\n│    └─── \"Real-time data access without refresh delays\"\n│         │\n│         └─── Question 2: Does the source database support query folding efficiently?\n│              │\n│              ├─── YES → **Choose DIRECTQUERY MODE**\n│              │         ✓ Unlocks: Live connection to source with every user interaction\n│              │         ✓ Enables: Real-time insights without data duplication\n│              │         ✓ Best suited for: Operational dashboards requiring current-minute data\n│              │         ✓ Optimized for: Sources with <1M row result sets and indexed tables\n│              │         ✓ Design for: Simple aggregations and filtered queries\n│              │         → Implement source-side performance optimization\n│              │\n│              └─── NO → Consider **COMPOSITE MODEL** (Hybrid Approach)\n│                        ✓ Unlocks: Combination of Import speed + DirectQuery freshness\n│                        ✓ Enables: Import for historical dimensions, DirectQuery for live facts\n│                        ✓ Best suited for: Mixed requirements where some tables need real-time data\n│                        ✓ Optimized for: Reducing DirectQuery load while maintaining freshness\n│\n└─── Question 1 Alternative: \"Do you need to connect to Analysis Services or Power BI datasets?\"\n     │\n     └─── YES → **Choose LIVE CONNECTION MODE**\n               ✓ Unlocks: Direct query against pre-modeled semantic layers\n               ✓ Enables: Centralized model governance with distributed reporting\n               ✓ Best suited for: Enterprise scenarios with certified datasets\n               ✓ Optimized for: Consistent metrics across multiple report authors\n               ✓ Design for: Report-level visuals only (no data modeling in report file)\n```\n\n---\n\n## Decision Tree 2: DAX Calculation Type Selection (Calculated Column vs Measure vs Calculated Table)\n\n**Decision Question:** \"Which DAX calculation type provides the capabilities I need?\"\n\n```\nSTART: Determining DAX Calculation Strategy\n│\n├─── Question 1: When does the calculation need to evaluate?\n│    │\n│    ├─── \"Once during data refresh, stored in the model\"\n│    │    │\n│    │    └─── Question 2: What is the calculation based on?\n│    │         │\n│    │         ├─── \"Row-by-row evaluation using columns in the same table\"\n│    │         │    │\n│    │         │    └─── **Choose CALCULATED COLUMN**\n│    │         │         ✓ Unlocks: Row context evaluation for each record\n│    │         │         ✓ Enables: Categorization, concatenation, and row-level logic\n│    │         │         ✓ Best suited for: Creating filter attributes (e.g., Age Groups, Price Bands)\n│    │         │         ✓ Optimized for: Supporting slicers, row-level security, and hierarchies\n│    │         │         ✓ Design for: Non-aggregated values needed for filtering/grouping\n│    │         │         → Storage impact: Increases model size (stored per row)\n│    │         │\n│    │         └─── \"Combining or transforming entire tables\"\n│    │              │\n│    │              └─── **Choose CALCULATED TABLE**\n│    │                   ✓ Unlocks: Table-level transformations using DAX expressions\n│    │                   ✓ Enables: Date tables, parameter tables, and reference tables\n│    │                   ✓ Best suited for: Creating disconnected tables for what-if analysis\n│    │                   ✓ Optimized for: Scenarios where Power Query isn't ideal (e.g., date tables)\n│    │                   ✓ Design for: Static reference data that changes with refresh\n│    │                   → Use case: CALENDAR(), GENERATESERIES(), SUMMARIZE() patterns\n│    │\n│    └─── \"Dynamically at query time based on filter context\"\n│         │\n│         └─── **Choose MEASURE**\n│              ✓ Unlocks: Dynamic aggregation responding to visual filters\n│              ✓ Enables: SUM, AVERAGE, COUNT, and complex business logic\n│              ✓ Best suited for: KPIs, metrics, and aggregated calculations\n│              ✓ Optimized for: Calculations that change based on user selections\n│              ✓ Design for: All numeric results in visuals (avoid calculated columns for aggregates)\n│              │\n│              └─── Question 2: Does the calculation require row-by-row iteration?\n│                   │\n│                   ├─── NO → Use simple aggregation functions\n│                   │         Examples: SUM([Sales]), AVERAGE([Quantity])\n│                   │         ✓ Provides: Engine optimization through formula engine\n│                   │\n│                   └─── YES → Use iterator functions (SUMX, AVERAGEX)\n│                             Examples: SUMX(Sales, [Quantity] * [Price])\n│                             ✓ Unlocks: Custom row-level logic within aggregation\n│                             ✓ Enables: Calculations not possible with simple SUM\n│                             ✓ Best suited for: Weighted averages, custom totals\n│                             → Performance: Use variables to avoid recalculation\n```\n\n---\n\n## Decision Tree 3: Report Distribution Method Selection\n\n**Decision Question:** \"Which distribution approach provides the collaboration and security capabilities stakeholders need?\"\n\n```\nSTART: Selecting Report Distribution Strategy\n│\n├─── Question 1: What is the primary stakeholder access pattern?\n│    │\n│    ├─── \"Frequent monitoring of live data with personalized filters\"\n│    │    │\n│    │    └─── Question 2: Do stakeholders need to edit or just consume?\n│    │         │\n│    │         ├─── \"Consume only with governed content\"\n│    │         │    │\n│    │         │    └─── **Choose POWER BI APP**\n│    │         │         ✓ Unlocks: Curated experience with bundled reports and dashboards\n│    │         │         ✓ Enables: One-click deployment to large audiences\n│    │         │         ✓ Best suited for: Departmental or company-wide distribution\n│    │         │         ✓ Optimized for: End users who don't need workspace access\n│    │         │         ✓ Design for: Organized navigation with sections and descriptions\n│    │         │         → Assign workspace roles: Viewers get app access, not workspace access\n│    │         │         → Update propagation: Publish app updates when reports change\n│    │         │\n│    │         └─── \"Collaborate and build together\"\n│    │              │\n│    │              └─── **Choose WORKSPACE SHARING with appropriate roles**\n│    │                   ✓ Unlocks: Direct workspace access for collaboration\n│    │                   ✓ Enables: Admin (manage), Member (publish), Contributor (edit), Viewer (view only)\n│    │                   ✓ Best suited for: Development teams and power users\n│    │                   ✓ Optimized for: Iterative report development and dataset reuse\n│    │                   ✓ Design for: Clear role assignment based on responsibilities\n│    │                   → Workspace capacity: Pro requires Pro licenses for all members\n│    │\n│    ├─── \"Scheduled delivery of static snapshots\"\n│    │    │\n│    │    └─── Question 2: What format serves the recipient's workflow?\n│    │         │\n│    │         ├─── \"PDF for executive review or archival\"\n│    │         │    │\n│    │         │    └─── **Choose SUBSCRIPTION with PDF export**\n│    │         │         ✓ Unlocks: Automated email delivery on schedule\n│    │         │         ✓ Enables: Point-in-time snapshots for record-keeping\n│    │         │         ✓ Best suited for: Board reports, monthly executive summaries\n│    │         │         ✓ Optimized for: Recipients without Power BI licenses\n│    │         │         → Configuration: Set frequency (daily, weekly, monthly)\n│    │         │         → Filter state: Captures current filter context at send time\n│    │         │\n│    │         ├─── \"PowerPoint for presentation integration\"\n│    │         │    │\n│    │         │    └─── **Choose EXPORT to PowerPoint**\n│    │         │         ✓ Unlocks: Embedded visuals in presentation format\n│    │         │         ✓ Enables: Integration with existing slide decks\n│    │         │         ✓ Best suited for: Conference presentations and client meetings\n│    │         │\n│    │         └─── \"Excel for further analysis\"\n│    │              │\n│    │              └─── **Choose ANALYZE IN EXCEL or Export Data**\n│    │                   ✓ Unlocks: PivotTable connection to semantic model (Analyze in Excel)\n│    │                   ✓ Enables: Ad-hoc slicing in familiar Excel environment\n│    │                   ✓ Best suited for: Analysts who prefer Excel for exploration\n│    │                   ✓ Optimized for: Scenarios requiring Excel formulas or custom layouts\n│    │\n│    ├─── \"Embedded within collaboration tools\"\n│    │    │\n│    │    └─── Question 2: Which platform hosts the primary workflow?\n│    │         │\n│    │         ├─── \"Microsoft Teams for discussion and decisions\"\n│    │         │    │\n│    │         │    └─── **Choose EMBED in Teams (Tab or Chat)**\n│    │         │         ✓ Unlocks: In-context analytics during team conversations\n│    │         │         ✓ Enables: Data-driven discussions without switching apps\n│    │         │         ✓ Best suited for: Project teams and operational meetings\n│    │         │         ✓ Optimized for: Teams with shared workspace access\n│    │         │         → Integration: Pin report as Teams tab or share link in channel\n│    │         │\n│    │         └─── \"SharePoint for document management\"\n│    │              │\n│    │              └─── **Choose EMBED in SharePoint Online**\n│    │                   ✓ Unlocks: Reports within SharePoint pages and portals\n│    │                   ✓ Enables: Unified intranet experience with embedded analytics\n│    │                   ✓ Best suited for: Corporate portals and departmental sites\n│    │                   ✓ Optimized for: Self-service access within existing navigation\n│    │\n│    └─── \"Formal reporting with strict layout control\"\n│         │\n│         └─── **Choose PAGINATED REPORTS (SSRS-style)**\n│              ✓ Unlocks: Pixel-perfect formatting for invoices, statements, and forms\n│              ✓ Enables: Multi-page documents with repeating headers/footers\n│              ✓ Best suited for: Operational reports requiring precise printing\n│              ✓ Optimized for: Line-item details and tabular layouts\n│              ✓ Design for: Scenarios where layout consistency matters more than interactivity\n│              → Storage: Requires Power BI Premium capacity or Premium Per User\n│\n└─── SPECIAL CONSIDERATION: Mobile-first audiences\n     │\n     └─── **Enable MOBILE LAYOUT optimization**\n          ✓ Unlocks: Touch-optimized experience on phones and tablets\n          ✓ Enables: Portrait-oriented canvas with reorganized visuals\n          ✓ Best suited for: Field teams and executives on the go\n          ✓ Optimized for: Single-column layouts and simplified navigation\n          → Design separately: Create mobile layout in Power BI Desktop\n```\n\n---\n\n**Framework Tree Navigation Note:** These three trees address the most frequent capability-matching decisions in PL-300. Each branch focuses on what the option enables rather than what it prevents, guiding selection through positive outcome criteria aligned with stakeholder needs and technical constraints.\n\n================================================================================\nMASTER HIERARCHICAL CHART\n================================================================================\n\n## STEP 3: MASTER HIERARCHICAL CHART\n\n```\n## 1. Power BI Service Workspace Management\n\n- PREPARE:\n  • Prerequisite: Power BI Pro license or Premium Per User (PPU) license to create workspaces; Power BI Free license limited to \"My Workspace\" only\n  • Selection: Choose between Workspace (supports collaboration, app publishing, deployment pipelines) vs. \"My Workspace\" (personal development only, no sharing capabilities)\n  • Execution: Navigate to Power BI Service (app.powerbi.com) > Workspaces pane > \"+ New workspace\" > Assign workspace name and Office 365 Group integration\n\n• MODEL:\n  • Workspace Access Role: Admin (full control, delete workspace), Member (publish/edit content), Contributor (publish content, no dataset management), Viewer (read-only access)\n  • Workspace License Mode: Configure as \"Pro\" (requires all users to have Pro licenses) or \"Premium capacity\" (assigned to P/EM SKU, allows Free license consumption)\n  • OneDrive for Business Integration: Enable \"Workspace OneDrive\" setting to store Excel workbooks with Power BI datasets in dedicated SharePoint library\n  • Deployment Pipeline Assignment: Attach workspace to Development/Test/Production stage in deployment pipelines for ALM (Application Lifecycle Management)\n  • Dataflow Storage: Configure Azure Data Lake Storage Gen2 (ADLS Gen2) connection for workspace dataflows via workspace settings > Azure connections\n  • Default Dataset Sensitivity Label: Set Microsoft Purview Information Protection label (e.g., \"Confidential\", \"General\") inherited by all new datasets\n  • **[Critical Distinction]:** Workspace (multi-user collaboration, supports deployment pipelines, app publishing to broader audience) vs. My Workspace (single-user sandbox, no deployment pipeline integration, cannot publish apps)\n  • **[Design Boundary]:** Maximum 1,000 workspaces per Power BI tenant; maximum 1,000 reports per workspace; workspace names must be unique across tenant\n  • **[Exam Focus]:** Understand workspace role permissions matrix (Admin/Member/Contributor/Viewer capabilities) and Premium vs. Pro licensing implications for content sharing (Exam objective: \"Manage workspaces and datasets\")\n\n○ DELIVER:\n  • Tool: Power BI Service Admin Portal > Usage Metrics > Workspace activity logs showing publish/refresh/view events\n  • Metric: Verify workspace capacity assignment in Capacity settings showing SKU allocation (e.g., \"P1\", \"A4\", \"EM3\") and memory utilization < 80%\n  • Validation: Confirm workspace appears in Deployment Pipeline view with correct stage assignment; test Viewer role user can access published reports but cannot edit datasets\n\n\n## 2. Power BI Desktop Environment\n\n- PREPARE:\n  • Prerequisite: Download Power BI Desktop from Microsoft Store (auto-updates enabled) or microsoft.com/power-bi (manual .exe installer, 64-bit recommended for >2GB datasets)\n  • Selection: Power BI Desktop (full authoring tool, .pbix files) vs. Power BI Desktop Optimized for Report Server (for on-premises PBIRS, separate download, limited feature set)\n  • Execution: Launch Power BI Desktop > Sign in with Azure AD organizational account (enables Power BI Service publishing) or continue unsigned (local development only, no publish capability)\n\n• MODEL:\n  • Report View: Canvas for building visualizations; includes Visualizations pane (chart types), Filters pane (page/visual/report level), Fields pane (model tables/columns)\n  • Data View: Table preview with column properties; access Column tools ribbon for Data type, Format, Summarization (Sum/Average/Count), Data category (e.g., Web URL, Image URL, Barcode)\n  • Model View: Visual relationship diagram; drag to create relationships, double-click to configure Cardinality (1:1, 1:*, *:*) and Cross filter direction (Single/Both)\n  • DAX Query View (Preview Feature): SQL-like query interface to test DAX table expressions using EVALUATE statement (e.g., EVALUATE SUMMARIZE('Sales', 'Product'[Category], \"Total\", SUM('Sales'[Amount])))\n  • Options > Data Load: Disable \"Autodetect new relationships after data is loaded\" to prevent unwanted relationship creation during Power Query refresh\n  • Options > Security: Enable \"Use enhanced metadata format\" for .pbix files (V3 format, improved performance, required for Premium features like large datasets)\n  • Performance Analyzer Tool: View ribbon > Performance analyzer > Start recording to capture DAX query duration, visual rendering time, and data retrieval milliseconds\n  • **[Critical Distinction]:** Report View (visualization authoring, user-facing design) vs. Data View (column-level configuration, data type validation) vs. Model View (relationship management, star schema validation)\n  • **[Design Boundary]:** .pbix file size limit 1GB for Power BI Service upload; maximum 16,000 columns per dataset; maximum 2 billion rows per table (Import mode only)\n  • **[Exam Focus]:** Navigate four core views (Report/Data/Model/DAX Query), understand Performance Analyzer output interpretation (Exam objective: \"Prepare the data\" and \"Model the data\")\n\n○ DELIVER:\n  • Tool: Performance Analyzer to capture baseline metrics; DAX Studio (external tool) for advanced query plan analysis showing Storage Engine/Formula Engine split\n  • Metric: Verify .pbix file size < 500MB for optimal upload performance; DAX query duration < 120ms per visual (Performance Analyzer benchmark)\n  • Validation: Open .pbix in Power BI Desktop > Model view > confirm all relationships show correct cardinality glyphs (1 or * on each end) and no red warning indicators\n\n\n## 3. Data Source Connectivity\n\n- PREPARE:\n  • Prerequisite: Install appropriate data gateway (On-premises data gateway for DirectQuery/scheduled refresh, or Personal gateway for personal cloud refresh) and configure firewall rules for outbound TCP 443\n  • Selection: Choose connector from Get Data dialog (300+ options): File sources (Excel, CSV, JSON), Databases (SQL Server, Oracle, MySQL), Cloud services (Azure SQL Database, SharePoint Online, Dynamics 365), Web (HTML tables, REST APIs)\n  • Execution: Home ribbon > Get Data > Search connector name (e.g., \"SQL Server\") > Enter Server name and Database name > Select Data Connectivity mode: Import vs. DirectQuery vs. Live Connection\n\n• MODEL:\n  • SQL Server Connection: Authentication modes include Windows (Kerberos/NTLM), Database (SQL auth credentials), Microsoft account (Azure AD integrated authentication for Azure SQL Database)\n  • Excel Workbook Source: Navigate to Table/Range vs. Sheet (imports all data including non-table areas); enable \"First row as headers\" Navigator option for structured tables\n  • Web.Contents() M Function: In Power Query Advanced Editor, specify URL with dynamic parameters: `= Web.Contents(\"https://api.example.com/data\", [RelativePath=\"endpoint\", Query=[date=\"2024-01-01\"]])`\n  • OData Feed Connector: Connect to SharePoint Online lists or Dynamics 365 entities using OData protocol; configure $select, $filter, $expand query parameters in Navigator advanced options\n  • Folder Connector: Aggregate multiple files from directory; Power Query automatically detects schema and generates \"Combine Files\" transformation; requires consistent column structure across files\n  • Parameters for Dynamic Connections: Create Parameter (Manage Parameters > New) with Type = Text, Current Value = server name; reference in Source step as `Sql.Database(ServerParameter, \"DatabaseName\")`\n  • Privacy Levels: Set per data source in Privacy tab: Public (can be combined with any source), Organizational (combine with other Organizational/Public), Private (isolate from other sources, prevents query folding across boundaries)\n  • **[Critical Distinction]:** Import mode (data copied into .pbix, fast queries, up to 1GB limit) vs. DirectQuery (live queries to source, no data copy, slower performance, row-level security delegation) vs. Live Connection (analysis services only, no Power Query transformations)\n  • **[Design Boundary]:** DirectQuery supports limited data sources: SQL Server, Azure SQL Database, Azure Synapse, Oracle, Teradata, SAP HANA, SAP BW; many connectors are Import-only (e.g., Excel, CSV, Web)\n  • **[Exam Focus]:** Identify correct connector for scenario (e.g., SharePoint list = SharePoint Online list connector, not Excel connector), understand authentication methods per source (Exam objective: \"Prepare the data - Get data from data sources\")\n\n○ DELIVER:\n  • Tool: Power Query Editor > View tab > Query Dependencies to visualize source-to-output data lineage and identify circular reference errors\n  • Metric: Check Applied Steps pane showing \"Source\" step with correct connection string; validate no \"DataSource.Error\" in preview pane\n  • Validation: Test connection by clicking \"Refresh Preview\" in Power Query Editor; verify row count matches expected source record count; check data types auto-detected correctly (e.g., decimal vs. text)\n\n\n## 4. Power Query Editor (M Language)\n\n- PREPARE:\n  • Prerequisite: Access Power Query Editor via Home ribbon > Transform Data (opens existing queries) or Get Data > [Source] > Transform Data (creates new query)\n  • Selection: Use Query Editor UI transformations (Generate M code automatically) vs. Advanced Editor (manually write/edit M script) vs. Custom Column formula bar (single-column M expressions)\n  • Execution: Right-click column header > Transform submenu for UI-driven operations (e.g., Replace Values, Split Column, Extract); or click Advanced Editor to view/edit full M script\n\n• MODEL:\n  • M Language Structure: let...in expression with sequential steps: `let Source = Excel.Workbook(...), FilteredRows = Table.SelectRows(Source, each [Amount] > 100) in FilteredRows`\n  • Applied Steps Pane: Each step references previous step name; right-click step > View Native Query (if query folding occurs) or Delete to remove transformation\n  • Table.SelectRows() Function: Filter rows using predicate function: `Table.SelectRows(#\"Previous Step\", each [Status] = \"Active\" and [Date] >= #date(2024,1,1))`\n  • Table.AddColumn() Function: Create calculated column referencing other columns: `Table.AddColumn(Source, \"Full Name\", each [First Name] & \" \" & [Last Name], type text)`\n  • Text.Split() and List.Last(): Extract substring from delimited text: `List.Last(Text.Split([Email], \"@\"))` to extract domain from email address\n  • Date.AddDays() and Duration.Days(): Date arithmetic: `Table.AddColumn(Source, \"Days Since\", each Duration.Days(DateTime.LocalNow() - [OrderDate]), Int64.Type)`\n  • Query Folding Indicator: Click \"View Native Query\" on Applied Step; if available, transformation pushed to source database (efficient); if greyed out, operation executes in Power Query engine (loads more data into memory)\n  • List.Generate() Function: Generate dynamic date table: `List.Generate(() => #date(2020,1,1), each _ <= #date(2024,12,31), each Date.AddDays(_, 1))` then convert to table\n  • **[Critical Distinction]:** Table.SelectRows (filters rows, reduces dataset size, supports query folding to SQL WHERE) vs. Table.SelectColumns (filters columns, reduces width, supports query folding to SQL SELECT clause)\n  • **[Design Boundary]:** M language is case-sensitive (Table.SelectRows ≠ table.selectrows); requires # prefix for special identifiers with spaces (#\"Column Name\"); maximum 1,000 Applied Steps per query (practical limit ~100 for maintainability)\n  • **[Exam Focus]:** Read M code to identify transformation sequence, understand when query folding breaks (e.g., after Table.Buffer(), custom M functions, or Text.Proper()), write basic M expressions in Custom Column (Exam objective: \"Prepare the data - Transform and load the data\")\n\n○ DELIVER:\n  • Tool: Power Query Editor > View tab > Query Dependencies (shows query reference relationships) and Formula Bar (displays M expression for selected Applied Step)\n  • Metric: Verify \"View Native Query\" available for critical filter/sort steps (indicates query folding success); Applied Steps count < 50 for optimal refresh performance\n  • Validation: Click Advanced Editor > validate M syntax highlighting (no red underlines); test query refresh with Refresh Preview button; confirm output row count and column data types match expectations\n\n\n## 5. Data Transformation and Cleaning\n\n- PREPARE:\n  • Prerequisite: Load data into Power Query Editor (Home > Transform Data); identify data quality issues using Column Quality, Column Distribution, Column Profile features (View tab > Data Preview section)\n  • Selection: Choose transformation approach: Remove Errors/Blanks (filters rows) vs. Replace Errors/Values (preserves row count) vs. Fill Down/Up (propagates values within column)\n  • Execution: Select column > Right-click header or use Transform ribbon tabs (e.g., Transform > Replace Values, Add Column > Custom Column, Home > Remove Rows > Remove Errors)\n\n• MODEL:\n  • Remove Duplicates: Select key columns (e.g., Customer ID, Order ID) > Home > Remove Rows > Remove Duplicates (keeps first occurrence, deletes subsequent matches based on selected columns only)\n  • Split Column by Delimiter: Transform > Split Column > By Delimiter > Select delimiter (comma, semicolon, custom) > Split at: Each occurrence (creates multiple columns) vs. Leftmost/Rightmost delimiter (creates 2 columns)\n  • Unpivot Columns: Select month columns (e.g., Jan, Feb, Mar) > Transform > Unpivot Columns > creates \"Attribute\" column (month names) and \"Value\" column (numeric values) for normalization\n  • Pivot Column: Select \"Attribute\" column > Transform > Pivot Column > Values Column: \"Value\" > Advanced options: Don't Aggregate (unique values) or Sum/Average/Count (aggregates)\n  • Replace Values with Error Handling: Transform > Replace Values > Value to Find: \"NULL\" > Replace With: null (blank) or \"0\"; use Table.ReplaceErrorValues() in M for programmatic approach\n  • Trim and Clean Text: Transform > Format > Trim (removes leading/trailing spaces) > Clean (removes non-printable characters) > Uppercase/Lowercase/Capitalize Each Word\n  • Column Data Type Inference: Power Query auto-detects types (\"ABC123\" heuristic); manually set via Transform > Data Type dropdown: Text (abc icon), Whole Number (123), Decimal Number (1.2), Date (calendar), Date/Time (calendar+clock)\n  • Merge Queries: Home > Merge Queries > Select tables and join columns > Join Kind: Left Outer (all from first, matching from second) vs. Inner (only matches) vs. Full Outer (all from both); expand resulting column to retrieve fields\n  • **[Critical Distinction]:** Unpivot (column headers become row values, ideal for month/year columns) vs. Pivot (row values become column headers, reverses unpivot operation); Merge Queries (horizontal join, adds columns) vs. Append Queries (vertical union, adds rows)\n  • **[Design Boundary]:** Replace Values is case-sensitive by default; Unpivot requires consistent data types across columns; Pivot creates one column per unique value (risk of column explosion with high cardinality fields)\n  • **[Exam Focus]:** Identify correct transformation for data shape issue (e.g., wide-to-long requires Unpivot, duplicate removal requires Remove Duplicates with key column selection), understand Merge vs. Append use cases (Exam objective: \"Prepare the data - Profile, clean, and transform the data\")\n\n○ DELIVER:\n  • Tool: Column Quality indicator (View tab > Data Preview > Column Quality enabled) showing percentage of Valid/Error/Empty values per column\n  • Metric: Target: 0% errors, <5% empty values for key columns; verify Column Distribution histogram shows expected value frequency (e.g., no unexpected spikes indicating data entry errors)\n  • Validation: Review Applied Steps pane for transformation sequence; use \"Close & Apply\" to load into model, then check Data view table preview for data accuracy and completeness\n\n\n## 6. Import vs DirectQuery vs Live Connection Storage Modes\n\n- PREPARE:\n  • Prerequisite: Understand data source connectivity mode requirements: Import (all sources supported), DirectQuery (limited sources: SQL Server, Azure SQL, Oracle, Teradata, SAP HANA), Live Connection (SSAS Tabular/Multidimensional, Power BI datasets only)\n  • Selection: Choose storage mode based on: Data freshness (Import = scheduled refresh vs. DirectQuery = real-time), Dataset size (Import ≤1GB limit vs. DirectQuery unlimited), Query performance (Import fast vs. DirectQuery dependent on source)\n  • Execution: During Get Data connection, select \"Import\" or \"DirectQuery\" radio button; or post-connection: Model view > select table > Properties pane > Storage mode dropdown\n\n• MODEL:\n  • Import Mode Characteristics: Data compressed and stored in VertiPaq in-memory engine; supports all Power Query transformations; maximum dataset size 1GB (Power BI Service upload), 10GB (Premium), 100GB (Premium Gen2 large datasets)\n  • DirectQuery Mode Characteristics: No data stored in .pbix; generates native SQL queries for each visual interaction; supports Row-Level Security (RLS) delegation to source; limited DAX functions (e.g., no TIME INTELLIGENCE functions without date table import)\n  • Live Connection Characteristics: Connects to published Power BI dataset or Azure Analysis Services/SSAS model; no Power Query transformations available; shares single semantic model across multiple reports\n  • Composite Models: Combine Import and DirectQuery tables in same model; enables DirectQuery to large fact table while importing dimension tables for performance; requires Power BI Premium or Premium Per User license for DirectQuery to Power BI dataset connections\n  • Storage Mode Property per Table: Right-click table in Model view > Properties > Storage mode: Import (data stored), DirectQuery (queries source), Dual (behaves as Import or DirectQuery depending on query context, optimizes performance)\n  • Aggregations: Pre-summarized Import table that serves queries against DirectQuery detail table; configure via Manage aggregations dialog: map aggregate table columns to detail table, specify summarization (Sum, Count, GroupBy)\n  • Query Reduction Options: File > Options > Current File > Query reduction: Reduce number of queries by adding \"Apply\" button to slicers/filters (prevents query-per-click in DirectQuery mode)\n  • **[Critical Distinction]:** Import (fast queries, scheduled refresh, 1GB limit, all transformations) vs. DirectQuery (near real-time, unlimited size, limited transformations, slower queries) vs. Live Connection (shared model, no transformations, centralized governance)\n  • **[Design Boundary]:** DirectQuery maximum 1 million rows returned per visual; calculated columns not supported in DirectQuery tables (use measures instead); DirectQuery to Power BI datasets requires Premium capacity\n  • **[Exam Focus]:** Select appropriate storage mode for scenario (e.g., real-time sales dashboard = DirectQuery, historical analysis with 10GB data = Import on Premium), understand Dual storage mode optimization logic (Exam objective: \"Model the data - Choose a storage mode\")\n\n○ DELIVER:\n  • Tool: Performance Analyzer to compare query duration: Import typically <100ms, DirectQuery 500ms-5s depending on source performance\n  • Metric: Import mode: check dataset size in Power BI Service workspace settings (target <500MB for non-Premium); DirectQuery: monitor Query duration in Performance Analyzer (target <3s per visual)\n  • Validation: Model view > verify Storage mode icon on each table: Import (table icon), DirectQuery (plug icon), Dual (double icon); test DirectQuery by applying filters and checking source database query logs for generated SQL\n\n\n## 7. Composite Models and Hybrid Tables\n\n- PREPARE:\n  • Prerequisite: Power BI Desktop version supporting Composite models (February 2018+); Premium or Premium Per User license for DirectQuery to Power BI datasets or Azure Analysis Services\n  • Selection: Composite Model topology: DirectQuery large fact table + Import dimension tables (star schema optimization) vs. Import aggregate table + DirectQuery detail table (aggregation pattern)\n  • Execution: Add DirectQuery connection to existing Import model: Get Data > [source] > Select DirectQuery mode > Power BI automatically enables Composite model with warning dialog\n\n• MODEL:\n  • Dual Storage Mode: Set dimension table to \"Dual\" (Properties > Storage mode: Dual) to allow Power BI query optimizer to materialize as Import when querying with Import tables, or reference as DirectQuery when querying with DirectQuery tables\n  • Aggregation Configuration: Model view > right-click aggregate table > Manage aggregations > Map: Detail Table (e.g., Sales), Detail Column (e.g., OrderDate), Summarization (e.g., GroupBy) > set Aggregate Column (e.g., OrderMonthKey)\n  • Aggregation Function Mapping: Sum (additive measures like Sales Amount), Count (row count), GroupBy (dimension attributes like ProductCategory), CountTableRows (counts distinct rows in detail table)\n  • Automatic Aggregation Routing: Power BI engine automatically routes queries to aggregate table when query grain matches; Detail table query executed only when aggregation cannot satisfy query (e.g., requesting day-level when aggregate is month-level)\n  • Incremental Refresh with Hybrid Tables (Premium): Configure Incremental refresh policy with \"Get the latest data in real time with DirectQuery\" enabled; historical partitions stored as Import, recent partition as DirectQuery for near real-time updates\n  • DirectQuery Source Group: Model view > Manage relationships > Advanced options > configure \"Source Group\" for DirectQuery connections to enable cross-source DirectQuery joins (requires compatible sources like SQL Server + Azure SQL Database)\n  • Limited Relationships: Between DirectQuery tables from different sources, only Many-to-Many relationships allowed unless configured as single source group\n  • **[Critical Distinction]:** Dual storage mode (table available in both Import/DirectQuery contexts, optimizes query performance automatically) vs. Import (always materialized) vs. DirectQuery (always queries source); Aggregation (automatic query routing) vs. Manual DirectQuery table (always queries source)\n  • **[Design Boundary]:** Composite models with DirectQuery to AS/PBI datasets cannot add calculated tables/columns to connected model; Aggregation tables must be Import mode; Maximum 100 aggregation definitions per model\n  • **[Exam Focus]:** Understand when to use Dual storage mode (dimension tables in mixed Import/DirectQuery model), configure aggregations for performance optimization, recognize incremental refresh hybrid table scenario (Exam objective: \"Model the data - Create model relationships\" and \"Optimize model performance\")\n\n○ DELIVER:\n  • Tool: Performance Analyzer with \"Include Queries\" enabled (under Start recording dropdown) > examine DirectQuery SQL queries vs. VertiPaq SE (Storage Engine) queries to aggregation tables\n  • Metric: Compare query duration before/after aggregation: DirectQuery detail table query 3-5s → Aggregation table query <200ms for matching grain; monitor Aggregation cache hit ratio in Premium metrics\n  • Validation: Model view > verify Dual icon (double stacked tables) on dimension tables; test aggregation routing by creating visual with aggregate grain (e.g., Sales by Month) → Performance Analyzer should show VertiPaq query, not DirectQuery SQL\n\n\n## 8. Data Refresh Configuration\n\n- PREPARE:\n  • Prerequisite: Publish .pbix to Power BI Service workspace; install and configure On-premises data gateway (Standard mode for shared gateway, Personal mode for individual use) if connecting to on-premises or network sources\n  • Selection: Refresh type: Scheduled refresh (time-based, up to 8x/day Pro, 48x/day Premium), On-demand refresh (manual trigger via dataset menu), API/PowerShell refresh (programmatic automation), Incremental refresh (Premium, partitioned historical data)\n  • Execution: Power BI Service > Workspace > Dataset > Settings (gear icon) > Scheduled refresh section > Configure gateway connection, credentials, and refresh schedule\n\n• MODEL:\n  • Gateway Connection Mapping: Settings > Gateway and cloud connections > select installed gateway from dropdown > Map data sources (ensure Source name matches connection string from Power Query Applied Steps)\n  • Data Source Credentials: Click \"Edit credentials\" for each mapped source > Authentication method: Windows (requires gateway service account with access), Database (SQL auth), OAuth2 (cloud services), Key (API keys)\n  • Scheduled Refresh Frequency: Enable \"Keep your data up to date\" toggle > Time zone selection > Add time slots (e.g., 6:00 AM, 12:00 PM, 6:00 PM); Pro: max 8/day, Premium: max 48/day (every 30 minutes)\n  • Refresh Failure Notifications: \"Send refresh failure notification email to\" recipients > includes dataset owner by default > add additional emails separated by semicolons; notifications sent when refresh fails twice consecutively\n  • Incremental Refresh Policy (Premium): Power BI Desktop > Table context menu > Incremental refresh > Define RangeStart and RangeEnd parameters (DateTime type) > Set Archive data starting: [X years before refresh] (Import), Refresh data starting: [Y days before refresh] (Import or Import+DirectQuery hybrid)\n  • Incremental Refresh Partitions: Archive data stored in monthly/yearly partitions (immutable); Recent data refreshed incrementally; \"Detect data changes\" column optional to refresh only changed partitions (e.g., ModifiedDate timestamp column)\n  • XMLA Endpoint Refresh (Premium): Connect external tools (e.g., SSMS, Tabular Editor, PowerShell) to dataset using XMLA endpoint (Workspace settings > Premium > XMLA Endpoint: Read-Write enabled) > execute TMSL ProcessFull/ProcessData commands\n  • **[Critical Distinction]:** Scheduled refresh (automatic timer-based, requires gateway for on-premises sources) vs. On-demand refresh (manual click, immediate execution) vs. Incremental refresh (partitioned approach, Premium only, reduces refresh time for large historical datasets)\n  • **[Design Boundary]:** Maximum refresh duration: 2 hours (Pro/PPU shared capacity), 5 hours (Premium per capacity SKU); Gateway supports max 10 concurrent refreshes; Incremental refresh requires RangeStart/RangeEnd parameters applied in Power Query filter steps\n  • **[Exam Focus]:** Configure gateway connection and credentials, set appropriate refresh schedule based on business requirements (e.g., daily 6 AM for overnight ETL), understand incremental refresh benefits for large fact tables (Exam objective: \"Deploy and maintain assets - Manage datasets\")\n\n○ DELIVER:\n  • Tool: Power BI Service > Dataset > Settings > Refresh history (shows last 30 refresh attempts with Status, Start time, Duration, Error details if failed)\n  • Metric: Target refresh duration <30 minutes for standard datasets, <2 hours for large datasets; Success rate >95% over 30-day period; verify gateway connectivity status \"Connected\" (green check)\n  • Validation: Test with \"Refresh now\" button in dataset menu > monitor Refresh history for \"Completed\" status; check report visuals update with latest data; review gateway logs (C:\\ProgramData\\Microsoft\\On-premises data gateway\\Logs) for connection errors if refresh fails\n\n\n## 9. Star Schema Design\n\n- PREPARE:\n  • Prerequisite: Understand dimensional modeling concepts: Fact table (measures, foreign keys, high row count) vs. Dimension table (attributes, primary keys, low row count) vs. Snowflake (normalized dimensions) vs. Star (denormalized dimensions)\n  • Selection: Identify Fact table(s) containing quantitative measures (Sales Amount, Quantity, Cost) and Dimension tables containing descriptive attributes (Product, Customer, Date, Geography)\n  • Execution: Model view > arrange tables visually with Fact table(s) center, Dimension tables surrounding; create relationships by dragging primary key (1-side) to foreign key (*-side)\n\n• MODEL:\n  • Date Dimension Table: Create dedicated Date table using DAX: `Date = CALENDAR(DATE(2020,1,1), DATE(2025,12,31))` or Power Query: `= {Number.From(#date(2020,1,1))..Number.From(#date(2025,12,31))}` > add calculated columns: Year, Quarter, Month, WeekNum\n  • Mark as Date Table: Select Date table > Table tools ribbon > Mark as date table > Select Date column as unique identifier (enables time intelligence functions like TOTALYTD, SAMEPERIODLASTYEAR)\n  • Relationship Cardinality: One-to-Many (1:*) from Dimension (primary key, unique values) to Fact (foreign key, duplicate values); avoid Many-to-Many (*:*) unless bridging tables or complex scenarios (performance impact)\n  • Cross Filter Direction: Single (default, filters flow from 1-side to *-side, dimension filters fact) vs. Both (bi-directional, enables filtering both directions, use sparingly due to ambiguity risks and performance overhead)\n  • Active vs Inactive Relationships: Maximum 1 active relationship between two tables; additional relationships marked inactive (dotted line); activate in DAX using USERELATIONSHIP function (e.g., `CALCULATE([Sales], USERELATIONSHIP(Sales[ShipDateKey], Date[DateKey]))`)\n  • Role-Playing Dimensions: Single Date table with multiple relationships to Fact table (e.g., OrderDate, ShipDate, DueDate); only one active, others inactive; create calculation groups or separate measures for each date role\n  • Surrogate Keys: Fact table foreign keys should reference integer surrogate keys (DateKey = 20240115) rather than Date/DateTime columns for optimal compression and relationship performance\n  • **[Critical Distinction]:** Star schema (denormalized dimensions, 1-level hierarchy, optimal Power BI performance) vs. Snowflake schema (normalized dimensions, multi-level joins, avoid in Power BI due to complexity and performance impact)\n  • **[Design Boundary]:** Limit dimension table columns to <100 for optimal performance; avoid high-cardinality dimension tables (>1 million rows) unless necessary; recommended maximum 30 relationships per model for maintainability\n  • **[Exam Focus]:** Identify fact vs. dimension tables in scenario, configure correct cardinality (1:*), create Date table and mark as date table, understand when to use Both cross filter direction (e.g., supporting count of related records) (Exam objective: \"Model the data - Design a semantic model\")\n\n○ DELIVER:\n  • Tool: Model view visual layout with Fact table(s) center, Dimensions radiating outward; View ribbon > Display options > Show relationship cardinality labels (1, *) and cross filter arrows\n  • Metric: Verify each Fact table has minimum 1 relationship to Date dimension (1:*); check that no Many-to-Many relationships exist unless intentionally designed; validate dimension tables have <1M rows\n  • Validation: Test relationship integrity: Create Matrix visual with Dimension attribute (rows) and Fact measure (values) > verify results match expectations; check for blank rows indicating missing dimension records (referential integrity issues)\n\n\n## 10. Table Relationships and Cardinality\n\n- PREPARE:\n  • Prerequisite: Access Model view in Power BI Desktop; ensure related columns have compatible data types (e.g., Integer to Integer, Text to Text; DateTime requires exact match including time component)\n  • Selection: Relationship type based on key uniqueness: One-to-Many (1:*) for primary key to foreign key, One-to-One (1:1) for merging tables with unique keys, Many-to-Many (*:*) for bridging scenarios or non-unique keys on both sides\n  • Execution: Model view > drag column from one table to related column in another table > Relationship dialog opens with auto-detected cardinality and cross filter direction > confirm or adjust settings > click OK\n\n• MODEL:\n  • Cardinality Detection: Power BI analyzes column values: 1 (unique values only, primary key), * (duplicate values, foreign key) > Auto-detects: 1:* (most common), 1:1 (both unique), *:* (both have duplicates)\n  • Many-to-Many Relationship Without Bridge: Directly relate tables with non-unique keys on both sides (e.g., Customer to Product via Many-to-Many Orders bridge); creates limited relationship with both-directional filtering by default\n  • Cross Filter Direction Configuration: Single (default for 1:*, filters flow from 1 to *), Both (bi-directional, enables filtering from * to 1, use for count of related records or bidirectional slicing, can cause ambiguity)\n  • Relationship Active Status: Solid line = Active (used by default in calculations), Dashed line = Inactive (requires USERELATIONSHIP function); scenario: multiple date relationships from Fact to Date dimension (OrderDate active, ShipDate inactive)\n  • Assume Referential Integrity (DirectQuery): Checkbox option in relationship properties; when enabled, Power BI generates INNER JOIN SQL instead of OUTER JOIN (performance optimization, only use when referential integrity guaranteed in source)\n  • Relationship Properties Dialog: From/To table and column, Cardinality dropdown (1:*, 1:1, *:*), Cross filter direction (Single, Both), \"Make this relationship active\" checkbox, \"Assume referential integrity\" (DirectQuery only)\n  • Bidirectional Filtering Ambiguity Risk: Both cross filter direction on multiple relationships creates filter propagation ambiguity; can cause unexpected results or DAX errors; limit Both direction to single path or carefully controlled scenarios\n  • USERELATIONSHIP Function: Activate inactive relationship in measure context: `Ship Date Sales = CALCULATE([Total Sales], USERELATIONSHIP(Sales[ShipDateKey], 'Date'[DateKey]))` allows multiple date role calculations\n  • **[Critical Distinction]:** 1:* (standard fact-to-dimension, single direction default, optimal performance) vs. *:* (bridging or non-unique keys, both direction required, creates limited relationship, potential performance impact); Active vs. Inactive (only one active between two tables, inactive requires USERELATIONSHIP)\n  • **[Design Boundary]:** Maximum 1 active relationship between two tables; Power BI prevents creating duplicate active relationships; Many-to-Many relationships use intermediate table internally, consuming memory; Both cross filter direction increases evaluation complexity\n  • **[Exam Focus]:** Select correct cardinality for scenario, understand when to use Both cross filter direction (e.g., customer count from sales table), recognize role-playing dimension pattern requiring inactive relationships (Exam objective: \"Model the data - Create model relationships\")\n\n○ DELIVER:\n  • Tool: Model view > View ribbon > Display options > enable \"Show relationship cardinality\" and \"Show cross filter direction\" arrows to visualize relationship configuration\n  • Metric: Verify cardinality symbols match design: 1 on dimension (primary key), * on fact (foreign key); count relationships with Both cross filter direction (target: <3 to avoid ambiguity)\n  • Validation: Test relationship by creating visual: dimension attribute as slicer, fact measure as card visual > verify measure filters correctly; check for unexpected blank results indicating broken relationship or data type mismatch\n```\n\n```\n## 11. DAX Calculated Columns\n- PREPARE:\n  • Prerequisite: Data model loaded in Power BI Desktop with at least one fact table in Import or DirectQuery mode\n  • Selection: Choose between Calculated Column (computed row-by-row at refresh) vs. Power Query Custom Column (computed at ETL) vs. Measure (computed at query time)\n  • Execution: Table view > Select target table in Fields pane > Table Tools > New Column > Enter DAX formula in formula bar\n• MODEL:\n  • **Column Name Syntax**: `Profit = Sales[Revenue] - Sales[Cost]` (spaces allowed, brackets for table reference)\n  • **Row Context Formula**: `FullName = Customers[FirstName] & \" \" & Customers[LastName]` (evaluates per row automatically)\n  • **RELATED() for Lookups**: `OrderCategory = RELATED(Products[Category])` (traverses many-to-one relationship from Orders to Products)\n  • **Column Data Type**: Set explicitly via Modeling tab > Data Type dropdown (Text, Whole Number, Decimal, Date/Time, True/False)\n  • **Storage Impact**: Calculated columns increase .pbix file size and memory consumption (stored in VertiPaq compression)\n  • **[Critical Distinction]:** Calculated Column (computed once at refresh, stored in model) vs. Measure (computed dynamically per visual query, not stored)\n  • **[Design Boundary]:** Cannot reference Measures in calculated column formulas; only other columns and DAX scalar functions allowed\n  • **[Exam Focus]:** Know when to use RELATED() vs. RELATEDTABLE() (one-to-many requires RELATEDTABLE with aggregation)\n○ DELIVER:\n  • Tool: Data view > Column Statistics (View tab > Data Preview > Column Quality/Distribution/Profile)\n  • Metric: Verify Distinct Count matches expected cardinality; check for blank values percentage\n  • Validation: Use DAX Studio > View Metrics tab to confirm column compression ratio (target > 10:1 for efficient storage)\n\n## 12. DAX Measures and Implicit Measures\n- PREPARE:\n  • Prerequisite: Fact table with numeric columns loaded in Power BI Desktop Import mode (DirectQuery supports explicit measures only)\n  • Selection: Implicit Measure (auto-created by dragging numeric field to visual) vs. Explicit Measure (manually defined with DAX) vs. Quick Measure (wizard-generated template)\n  • Execution: Home tab > New Measure > Enter formula like `Total Sales = SUM(Sales[Amount])` OR drag numeric field to Values well (creates implicit Sum of Amount)\n• MODEL:\n  • **Explicit Measure Syntax**: `Total Revenue = SUM(Sales[SalesAmount])` (no table prefix on measure name, aggregation function required)\n  • **Implicit Measure Creation**: Drag Sales[Amount] to visual Values well → Power BI creates hidden \"Sum of Amount\" measure automatically\n  • **Implicit Measure Limitation**: Cannot modify DAX formula; limited to SUM, COUNT, MIN, MAX, AVG, DISTINCTCOUNT aggregations\n  • **Measure Home Table**: Right-click measure > Move to Home Table to organize in Display Folder hierarchy for field list clarity\n  • **Format String**: Measure > Modeling tab > Format: Currency ($#,0) or Percentage (0.00%) or Custom (\"$\"#,0.0,\"K\")\n  • **CALCULATE() Wrapper**: `Sales LY = CALCULATE(SUM(Sales[Amount]), SAMEPERIODLASTYEAR(Dates[Date]))` (modifies filter context)\n  • **[Critical Distinction]:** Implicit measures cannot be referenced in other DAX formulas; convert to explicit measure to enable reuse\n  • **[Design Boundary]:** DirectQuery mode requires explicit measures only; implicit measures disabled for non-Import connections\n  • **[Exam Focus]:** Understand filter context flows from visuals to measures; slicers and filters modify CALCULATE's internal filter arguments\n○ DELIVER:\n  • Tool: Performance Analyzer (View tab > Performance Analyzer > Start Recording) to measure DAX query duration\n  • Metric: Explicit measure query time should be < 120ms for responsive visuals; implicit measures typically 20-40% slower due to metadata overhead\n  • Validation: DAX Studio > Server Timings pane to view Formula Engine vs. Storage Engine duration split\n\n## 13. DAX Iterator Functions (SUMX, AVERAGEX)\n- PREPARE:\n  • Prerequisite: Data model with related tables (e.g., Sales fact table related to Products dimension) in Power BI Desktop\n  • Selection: SUMX (iterates and sums), AVERAGEX (iterates and averages), RANKX (iterates and ranks), COUNTAX (counts non-blank iterations)\n  • Execution: New Measure > Enter `Total Margin = SUMX(Sales, Sales[Quantity] * RELATED(Products[UnitCost]))` for row-by-row calculation\n• MODEL:\n  • **SUMX Syntax**: `Revenue = SUMX(Sales, Sales[Quantity] * Sales[UnitPrice])` (first argument = table, second = expression evaluated per row)\n  • **AVERAGEX with Filter**: `Avg Price = AVERAGEX(FILTER(Products, Products[Category] = \"Electronics\"), Products[ListPrice])` (filtered iterator)\n  • **RANKX for Ranking**: `Product Rank = RANKX(ALL(Products), [Total Sales],, DESC, Dense)` (ranks products by Total Sales descending with dense ranking)\n  • **Iterator Performance**: Minimize nested iterators (e.g., avoid SUMX inside FILTER inside SUMX); use variables to store subtables\n  • **Row Context Creation**: Iterator functions automatically create row context for expression evaluation; no CALCULATE needed for context transition\n  • **CALCULATE in Iterator**: `Profit = SUMX(Sales, Sales[Amount] - CALCULATE(SUM(Costs[Cost])))` forces context transition from row to filter context\n  • **[Critical Distinction]:** SUM(Sales[Amount]) (aggregates column directly) vs. SUMX(Sales, Sales[Quantity] * Sales[Price]) (computes per row then sums)\n  • **[Design Boundary]:** Iterators create storage engine queries per row in large tables; prefer calculated columns for static row-level math when possible\n  • **[Exam Focus]:** Know COUNTAX counts non-blank results vs. COUNTX counts all rows iterated; AVERAGEX excludes blanks automatically\n○ DELIVER:\n  • Tool: DAX Studio > Query Plan tab > Physical Query Plan to identify Storage Engine scan operations\n  • Metric: Scan Count should be minimal (< 5 scans); SE CPU Time should be < 80% of total query time\n  • Validation: Compare SUMX measure performance against equivalent Calculated Column + SUM() approach using Performance Analyzer Duration metric\n\n## 14. DAX Filter Context and Row Context\n- PREPARE:\n  • Prerequisite: Power BI Desktop with multi-table data model (minimum one fact table with related dimension tables)\n  • Selection: Filter Context (from slicers, visual filters, row/column labels) vs. Row Context (from calculated columns, iterators) vs. Query Context (from Evaluate in DAX Studio)\n  • Execution: Create measure `Sales Amount = SUM(Sales[Amount])` then add to visual with Category slicer to observe filter context modification\n• MODEL:\n  • **Filter Context Definition**: Set of filters applied to all tables in data model when evaluating measure (e.g., Year=2024 + Region=\"East\" from slicers)\n  • **Row Context Definition**: Current row being evaluated in calculated column or iterator function (e.g., Sales[Quantity] * Sales[Price] operates in row context)\n  • **Context Transition**: `Total = CALCULATE(SUM(Sales[Amount]))` inside SUMX converts row context to filter context using CALCULATE\n  • **ALL() Removes Filters**: `Total All Sales = CALCULATE([Total Sales], ALL(Products))` ignores Products filters from visual but keeps other filters\n  • **ALLSELECTED() Preserves Outer**: `Percent of Parent = DIVIDE([Total Sales], CALCULATE([Total Sales], ALLSELECTED(Products[Category])))` keeps report-level filters\n  • **FILTER() Creates Row Context**: `High Value = CALCULATE([Total Sales], FILTER(Sales, Sales[Amount] > 1000))` iterates Sales rows with row context\n  • **KEEPFILTERS() Preserves Existing**: `Sales with Keep = CALCULATE([Total Sales], KEEPFILTERS(Products[Color] = \"Red\"))` adds to existing filter instead of replacing\n  • **[Critical Distinction]:** Row context does NOT automatically filter related tables; use RELATED() or CALCULATE for context transition to filter dimension tables\n  • **[Design Boundary]:** Calculated columns operate in row context only; cannot directly reference measures (which require filter context)\n  • **[Exam Focus]:** Understand CALCULATE()'s two roles: modify filter context in measures AND transition row context to filter context in iterators\n○ DELIVER:\n  • Tool: DAX Studio > Query Builder to test measures with explicit FILTER() statements and view results by filter combination\n  • Metric: Use ADDCOLUMNS() to visualize current filter context: `EVALUATE ADDCOLUMNS(VALUES(Products[Category]), \"Sales\", [Total Sales])`\n  • Validation: Compare measure results with ALL() vs. ALLSELECTED() vs. no filter modification to confirm context behavior\n\n## 15. DAX Time Intelligence Functions\n- PREPARE:\n  • Prerequisite: Date table marked as Date Table (Table Tools > Mark as Date Table) with contiguous dates covering data range and linked to fact table via inactive/active relationship\n  • Selection: TOTALYTD/TOTALQTD (year/quarter-to-date), SAMEPERIODLASTYEAR (prior year), DATEADD (shift by N periods), PARALLELPERIOD (complete prior period)\n  • Execution: Modeling tab > New Measure > `YTD Sales = TOTALYTD(SUM(Sales[Amount]), Dates[Date])` (requires date table with Date column marked)\n• MODEL:\n  • **TOTALYTD Syntax**: `Sales YTD = TOTALYTD([Total Sales], Dates[Date])` (accumulates from Jan 1 to current filter date; optional year_end_date parameter)\n  • **SAMEPERIODLASTYEAR**: `Sales LY = CALCULATE([Total Sales], SAMEPERIODLASTYEAR(Dates[Date]))` (shifts filter context back 365 days; handles leap years)\n  • **DATEADD for Flexibility**: `Sales Prev Month = CALCULATE([Total Sales], DATEADD(Dates[Date], -1, MONTH))` (negative shifts backward, positive shifts forward)\n  • **PARALLELPERIOD Full Period**: `Sales Same Month LY = CALCULATE([Total Sales], PARALLELPERIOD(Dates[Date], -12, MONTH))` (returns complete month 12 months ago)\n  • **Year-over-Year Growth**: `YoY Growth % = DIVIDE([Total Sales] - [Sales LY], [Sales LY], 0)` (division by zero returns 0 with third parameter)\n  • **DATESYTD for Custom YTD**: `DATESYTD(Dates[Date], \"06-30\")` (fiscal year ending June 30 instead of calendar year)\n  • **DATESMTD and DATESQTD**: `MTD Sales = CALCULATE([Total Sales], DATESMTD(Dates[Date]))` (month-to-date) and DATESQTD for quarter-to-date\n  • **[Critical Distinction]:** SAMEPERIODLASTYEAR returns same dates last year (e.g., Jan 15 → Jan 15 prior year) vs. DATEADD(-365, DAY) shifts exactly 365 days (may land on different month/day)\n  • **[Design Boundary]:** Time intelligence functions require unbroken date range in Date table; missing dates cause incorrect accumulations in TOTALYTD\n  • **[Exam Focus]:** Know when to use PARALLELPERIOD (full period comparison) vs. SAMEPERIODLASTYEAR (partial period if current period incomplete)\n○ DELIVER:\n  • Tool: Power BI Desktop > Data view > Date table > Verify contiguous dates with no gaps using Column Quality (should show 0% Error, 0% Empty)\n  • Metric: Validate YTD measure on December 31 equals Total Sales for full year; validate SAMEPERIODLASTYEAR on Jan 2024 matches Jan 2023\n  • Validation: DAX Studio > `EVALUATE CALCULATETABLE(DATESYTD(Dates[Date]))` to inspect actual date range returned by time intelligence function\n\n## 16. DAX Variables and Query Performance\n- PREPARE:\n  • Prerequisite: Power BI Desktop with measures experiencing slow performance (> 200ms in Performance Analyzer) due to repeated subquery evaluation\n  • Selection: VAR keyword for storing intermediate results vs. inline repetition vs. calculated columns (for static pre-computation)\n  • Execution: Modify measure `Margin % = DIVIDE(SUM(Sales[Amount]) - SUM(Costs[Cost]), SUM(Sales[Amount]))` to use VAR for SUM(Sales[Amount]) reuse\n• MODEL:\n  • **VAR Syntax**: `VAR TotalSales = SUM(Sales[Amount]) VAR TotalCost = SUM(Costs[Cost]) RETURN DIVIDE(TotalSales - TotalCost, TotalSales)` (variable assignment then RETURN expression)\n  • **Multiple Variables**: Declare multiple VARs sequentially; each can reference prior variables (e.g., `VAR Margin = TotalSales - TotalCost`)\n  • **Materialization Benefit**: Variables store result once; repeated references use cached value instead of recomputing (reduces Storage Engine queries)\n  • **Table Variables**: `VAR TopProducts = TOPN(10, Products, [Total Sales], DESC) RETURN COUNTROWS(TopProducts)` (stores filtered table for reuse)\n  • **RETURN Requirement**: Every VAR block must end with RETURN statement; RETURN can be complex expression referencing all variables\n  • **Variable Scope**: Variables accessible only within measure definition; cannot be referenced in other measures or calculated columns\n  • **[Critical Distinction]:** Variables evaluated once at measure start vs. subqueries evaluated multiple times (e.g., DIVIDE denominator recalculated every reference without VAR)\n  • **[Design Boundary]:** Variables increase measure complexity; balance readability vs. performance gains (use for expressions repeated 3+ times)\n  • **[Exam Focus]:** Identify scenarios where VAR reduces query plan complexity: repeated aggregations, nested CALCULATE statements, complex FILTER expressions\n○ DELIVER:\n  • Tool: DAX Studio > Server Timings > compare Storage Engine Query Count before/after VAR introduction\n  • Metric: Target 30-50% reduction in SE queries when refactoring repeated SUM/COUNT expressions into variables\n  • Validation: Performance Analyzer > Compare measure Duration before/after VAR; verify Formula Engine time decreases (FE evaluates variables once)\n\n## 17. Row-Level Security (RLS)\n- PREPARE:\n  • Prerequisite: Power BI Desktop with published dataset to Power BI Service; Power BI Pro or Premium Per User license for RLS enforcement\n  • Selection: Static RLS (hardcoded DAX filters like `[Region] = \"West\"`) vs. Dynamic RLS (uses USERNAME() or USERPRINCIPALNAME() functions) vs. Object-Level Security (hides tables/columns)\n  • Execution: Modeling tab > Manage Roles > Create Role > Add DAX filter to table (e.g., `Sales[Region] = \"East\"`) > Publish to Service > Workspace Settings > Security\n• MODEL:\n  • **Role Creation**: Modeling > Manage Roles > New > Role Name: \"East Region\" > Table: Sales > Filter: `[Region] = \"East\"` (filters all rows to East region)\n  • **Dynamic RLS with USERNAME()**: `[Email] = USERNAME()` (filters to rows matching current user's email; USERNAME() returns \"domain\\user\" in Desktop, \"user@domain.com\" in Service)\n  • **USERPRINCIPALNAME() for Email**: `[UserEmail] = USERPRINCIPALNAME()` (always returns UPN format user@domain.com; preferred for email-based security tables)\n  • **Multiple Role Membership**: User assigned to multiple roles sees UNION of all allowed rows (OR logic, not AND); Service enforces at query time\n  • **RLS Testing in Desktop**: Modeling > View as Roles > Select role > Desktop applies filter to test visual results before publishing\n  • **Security Table Pattern**: Create separate Users table with [UserEmail] and [Region] columns; filter Users[UserEmail] = USERPRINCIPALNAME() and propagate via relationship\n  • **Bidirectional Filtering**: Set relationship to Both directions if security table is dimension; allows filter to flow from Users to Facts through dimension tables\n  • **[Critical Distinction]:** RLS filters rows (user sees subset of data) vs. Object-Level Security (user cannot see entire table/column in field list)\n  • **[Design Boundary]:** RLS not enforced for workspace Admins/Members/Contributors; only enforced for Viewers or via \"Test as Role\" in Service\n  • **[Exam Focus]:** Understand USERNAME() returns different formats in Desktop (domain\\user) vs. Service (user@domain.com); use USERPRINCIPALNAME() for consistency\n○ DELIVER:\n  • Tool: Power BI Service > Dataset Settings > Security tab > Add members to role > Test as Role to verify filtering\n  • Metric: Query filtered table with DAX Studio using EVALUATE syntax to confirm row count matches expected security boundary\n  • Validation: Publish report > Share with test user assigned to role > Verify visual shows only authorized rows (compare row count vs. Admin view)\n\n## 18. Object-Level Security (OLS)\n- PREPARE:\n  • Prerequisite: Power BI Desktop with published dataset to Premium workspace (Premium Per User, Premium capacity, or Embedded); Tabular Editor 2 or Tabular Editor 3 for external editing\n  • Selection: OLS hides entire tables/columns from roles (not visible in field list) vs. RLS filters rows (table visible but subset of data) vs. Column-Level Security in SQL (source-level hiding)\n  • Execution: Install Tabular Editor 2 > External Tools in Power BI Desktop > Tabular Editor > Right-click table/column > Object Level Security > Assign to Role\n• MODEL:\n  • **OLS via Tabular Editor**: Connect to model > Roles node > Create Role > Select table > Set \"Read\" permission to \"None\" (hides table) or \"Read\" (visible)\n  • **Column-Level OLS**: Right-click individual column > Properties > Set \"Column Permission\" to \"None\" for specific role (hides column from field list)\n  • **Permission Inheritance**: Default permission is \"Read\"; explicitly set \"None\" to hide; inheritance flows from table to columns unless column overridden\n  • **XMLA Endpoint Requirement**: OLS requires XMLA Read/Write endpoint (Premium or PPU); not available in Power BI Pro shared capacity\n  • **Combine with RLS**: Apply OLS to hide PII columns (e.g., SSN, Salary) AND RLS to filter rows by region (both enforced simultaneously)\n  • **Tabular Model Scripting Language (TMSL)**: Advanced OLS configuration via JSON scripts using TMSL commands (e.g., `\"metadataPermission\": \"none\"`)\n  • **[Critical Distinction]:** OLS hides objects from metadata (user cannot see field in list) vs. RLS returns zero rows when field used in visual (field visible but empty)\n  • **[Design Boundary]:** OLS requires Premium licensing; cannot be configured in Power BI Desktop UI (requires Tabular Editor or TMSL scripts via SSMS)\n  • **[Exam Focus]:** Know OLS enforced at metadata level (field list) before query execution vs. RLS enforced at query time (after user selects fields)\n○ DELIVER:\n  • Tool: Tabular Editor 2 > Model > Roles > Verify role shows \"None\" permission for hidden tables/columns in Object Level Security grid\n  • Metric: Connect to published dataset with test user assigned to OLS role; confirm hidden columns do not appear in Get Data > Analysis Services connector\n  • Validation: Power BI Service > Dataset > Explore data > Verify role-specific users cannot see OLS-protected columns in field well when building ad-hoc visuals\n\n## 19. Data Categorization and Hierarchies\n- PREPARE:\n  • Prerequisite: Power BI Desktop data model with dimension tables containing related attributes (e.g., Geography: Country > State > City)\n  • Selection: Data Category (URL, Image URL, Barcode, Geographic: Address/City/State/Country/Postal Code) vs. Default Summarization (Sum, Average, Count) vs. Sort By Column\n  • Execution: Model view > Select column > Column Tools > Data Category dropdown > Choose \"City\" or \"Web URL\" to enable map visuals or clickable links\n• MODEL:\n  • **Geographic Data Category**: Column > Data Category: \"City\", \"State or Province\", \"Country/Region\", \"Postal Code\" (enables ArcGIS Maps and Filled Map auto-field assignment)\n  • **Web URL Category**: Set Data Category to \"Web URL\" (e.g., `Products[ProductURL]`) enables table visual to render as clickable hyperlinks\n  • **Image URL for Visual**: Data Category: \"Image URL\" (e.g., `Products[ImageURL]`) allows table/matrix to display image thumbnails from URLs\n  • **Sort by Column**: Month Name column > Column Tools > Sort by Column: Month Number (sorts \"Jan, Feb, Mar\" instead of alphabetically \"Apr, Aug, Dec\")\n  • **Hierarchy Creation**: Model view > Right-click top-level column (e.g., Country) > Create Hierarchy > Add levels (State, City) via drag-and-drop to hierarchy node\n  • **Drill-Down Behavior**: Hierarchy enables drill-down in matrix/chart visuals; click category to expand from Country → State → City granularity automatically\n  • **Default Summarization**: Numeric column > Column Tools > Summarization: \"Don't Summarize\" (for ID fields), \"Sum\" (default for measures), \"Average\", \"Min/Max\"\n  • **[Critical Distinction]:** Data Category affects visual behavior (map auto-assign, URL rendering) vs. Sort by Column affects display order vs. Summarization affects aggregation method\n  • **[Design Boundary]:** Hierarchies limited to single table; cannot create hierarchy spanning multiple tables (e.g., Category from Products + Subcategory from Subcategories requires denormalization)\n  • **[Exam Focus]:** Know when to use \"Don't Summarize\" for text IDs (prevents meaningless SUM of Order ID) vs. \"Count\" for counting distinct records\n○ DELIVER:\n  • Tool: Model view > Column > Properties pane to verify Data Category, Sort by Column, and Summarization settings persisted correctly\n  • Metric: Create Filled Map visual > Verify automatic field assignment (Location auto-populated with City category field) without manual field dragging\n  • Validation: Matrix visual with hierarchy > Drill down from top level to confirm smooth expansion; verify Sort by Column shows chronological month order instead of alphabetical\n\n## 20. Visual Selection and Use Cases\n- PREPARE:\n  • Prerequisite: Power BI Desktop with analyzed dataset requirements (data types, cardinality, narrative goals: trend, comparison, distribution, composition)\n  • Selection: Line Chart (time trends), Clustered Bar Chart (category comparison), Pie/Donut (composition %), Scatter Chart (correlation), Table/Matrix (detailed drill-through)\n  • Execution: Visualizations pane > Select visual icon > Drag fields to Fields/Axis/Values wells > Format pane to customize appearance\n• MODEL:\n  • **Line Chart for Trends**: Axis: Date (continuous), Legend: Category, Values: SUM(Sales) (shows how metric changes over time; use for year-over-year comparisons)\n  • **Clustered Column Chart for Comparison**: Axis: Product Category, Values: Total Revenue (compares discrete categories side-by-side; use for ranking top N)\n  • **Stacked Bar Chart for Composition**: Axis: Region, Legend: Product Type, Values: Sales (shows part-to-whole within each category; use for market share)\n  • **Pie/Donut Chart Limitation**: Effective for 3-5 slices maximum; avoid for 10+ categories (human eye cannot distinguish small angle differences)\n  • **Scatter Chart for Correlation**: X-Axis: Advertising Spend, Y-Axis: Sales Revenue, Values: Store ID (identifies relationship strength; add trend line via Analytics pane)\n  • **Table vs. Matrix**: Table shows flat list (detail-level drill-through); Matrix shows rows + columns with subtotals (pivot table equivalent; use for cross-tab analysis)\n  • **Card Visual for KPIs**: Single metric display (e.g., Total Revenue, YTD Sales); use in dashboard top row for executive summary\n  • **Gauge for Target Tracking**: Value: Actual Sales, Target: Sales Goal, Min/Max: Performance thresholds (visual shows progress toward goal with color indicators)\n  • **Treemap for Hierarchical Composition**: Group: Category > Subcategory, Values: Sales Amount (rectangle size = value; use for part-to-whole with hierarchy)\n  • **ArcGIS Map for Geospatial**: Location: City (with Data Category set), Size: Sales (bubble map showing geographic distribution; requires ArcGIS account for advanced features)\n  • **[Critical Distinction]:** Line chart requires continuous axis (Date/Time) vs. Clustered column accepts categorical axis (Text, Whole Number as category)\n  • **[Design Boundary]:** Power BI visuals limited to 30,000 data points per visual in Desktop (3,500 in Service); use filters/aggregations to stay within limit\n  • **[Exam Focus]:** Understand visual selection criteria: Line (trend over time), Column (compare categories), Pie (composition %), Scatter (correlation between two metrics)\n○ DELIVER:\n  • Tool: Performance Analyzer (View tab) to measure visual rendering time; target < 300ms per visual for responsive dashboard experience\n  • Metric: Visual Query Duration should be < 200ms; DAX Query < 100ms; Other (rendering) < 100ms breakdown for optimization priorities\n  • Validation: Format pane > Title > Tooltip to add context; verify Data Labels toggle for bar/column charts improves readability without clutter\n```\n\n```\n## 21. Custom Visuals from AppSource\n- PREPARE:\n  • Prerequisite: Power BI Service account with permissions to import organizational visuals OR Power BI Desktop with internet connectivity to access AppSource marketplace\n  • Selection: AppSource marketplace hosts 300+ certified custom visuals (Chiclet Slicer, Zebra BI Tables, Enlighten Aquarium) vs. import from file (.pbiviz format) for organizational custom visuals vs. develop using Power BI Visuals SDK with TypeScript and D3.js libraries\n  • Execution: In Power BI Desktop, navigate to Visualizations pane > ellipsis (…) > Get more visuals > opens AppSource dialog OR import from organizational store if enabled by Power BI tenant admin\n• MODEL:\n  • **Visual Security Classification**: AppSource visuals marked as \"Certified\" undergo Microsoft security review vs. \"Non-certified\" visuals require admin approval in tenant settings under Custom visuals > Allow visuals from AppSource\n  • **Data Transmission Behavior**: Some custom visuals (e.g., map visuals, web content visuals) send data to external services—verify visual documentation for HTTPS endpoints and data egress requirements\n  • **Field Mapping Configuration**: Custom visuals expose unique field wells (e.g., Chiclet Slicer requires Fields + Values for dual-axis display; Power KPI Matrix requires Date + Indicator + Value + Target fields)\n  • **[Critical Distinction]:** Certified custom visuals (Zebra BI, MAQ Software gauges) can be deployed tenant-wide via Power BI Admin Portal > Tenant settings vs. Non-certified visuals require individual import per .pbix file and may be blocked by organizational policy\n  • **[Design Boundary]:** Custom visuals cannot access Power BI data model directly via DAX—they receive only filtered data passed to field wells, limiting real-time calculation capabilities compared to native visuals with implicit CALCULATE contexts\n  • **Performance Overhead**: Custom visuals load external JavaScript libraries (D3.js, WebGL renderers) which increase .pbix file size by 200KB-5MB per visual and add 100-500ms rendering time vs. native visuals optimized in Power BI engine\n  • **[Exam Focus]:** Skills measured include \"Select appropriate visualizations\" (understand when custom visuals from AppSource provide capabilities unavailable in native visuals like advanced Gantt charts, network graphs, or custom animations)\n  • **Update Management**: Custom visuals in .pbix files do NOT auto-update when AppSource releases new versions—must manually remove old visual and re-import updated version, reconfiguring field mappings and format settings\n○ DELIVER:\n  • Tool: Power BI Desktop > View tab > Performance Analyzer to measure custom visual render time vs. native visual baselines (target <200ms for page interactions)\n  • Metric: Check custom visual certification status in AppSource dialog—certified visuals display blue checkmark icon and Microsoft security review timestamp\n  • Validation: Test custom visual cross-filtering behavior with native slicers using Ctrl+Click on data points—verify bidirectional filter propagation appears correctly in Filter pane > Filters on this visual section\n  • Security Audit: For custom visuals accessing external services, review Power BI Admin Portal > Audit logs for \"GetCustomVisualDataExternally\" events showing data transmission outside organizational boundary\n\n## 22. Report Layout and Page Design\n- PREPARE:\n  • Prerequisite: Power BI Desktop report file (.pbix) with at least one data model table and measure defined for visual population\n  • Selection: Canvas size options include 16:9 (default 1280x720 optimized for presentation mode) vs. 4:3 (960x720 legacy format) vs. Tooltip (320x240 for report page tooltips) vs. Custom (specify exact pixel dimensions) configured in Page Settings > Canvas settings\n  • Execution: Right-click report page tab at bottom > Page Settings OR View tab > Page View dropdown (Fit to Page, Fit to Width, Actual Size affects design-time zoom only, not published report rendering)\n• MODEL:\n  • **Page Background**: Format pane > Canvas background > Image (upload .png/.jpg up to 25MB, stretches to canvas) vs. Color (solid fill with transparency 0-100%) vs. Wallpaper mode (tiles image instead of stretching, useful for watermarks)\n  • **Grid and Snap Settings**: View tab > Show gridlines (displays 10px grid by default) + Snap to grid (aligns visuals to nearest grid intersection) OR hold Alt while dragging to override snap temporarily for pixel-perfect positioning\n  • **Visual Layering**: Selection pane (View tab > Selection) displays visual Z-order from top to bottom—use \"Bring forward\" / \"Send backward\" buttons or drag visuals in list to control overlapping elements like background shapes behind KPI cards\n  • **Mobile Layout**: View tab > Mobile layout opens 9:16 portrait canvas (Phone layout) where you must explicitly drag visuals from Visualizations pane into mobile canvas—desktop visuals do NOT auto-appear in mobile view\n  • **[Critical Distinction]:** Page Size \"Custom\" allows exact pixel dimensions (e.g., 1920x1080 for full-HD displays) but published reports in Power BI Service always scale proportionally to browser window vs. Power BI Report Server preserves exact pixel dimensions for print-optimized reports\n  • **Themes**: View tab > Themes > Browse for themes applies JSON theme file defining default colors, fonts, and visual formatting—custom themes override individual visual format settings unless \"Customize current theme\" is used to create exceptions\n  • **Alignment Tools**: Format tab (appears when multiple visuals selected) > Align (Left, Right, Top, Bottom, Middle, Center) and Distribute (Horizontally, Vertically) ensure consistent spacing using largest visual as anchor point\n  • **[Design Boundary]:** Power BI Desktop canvas maximum size is 4096x4096 pixels—exceeding this in Custom page size results in error \"Canvas size exceeds maximum allowed dimensions\" and report fails to save\n  • **[Exam Focus]:** Skills measured include \"Design and configure for accessibility\" requiring knowledge of View tab > Page information > Alt text field (per visual) and Color > Background color contrast ratios meeting WCAG 2.1 AA standards (4.5:1 for normal text)\n  • **Section Headers**: Insert text box (Insert tab > Text box) formatted with Title font style (28pt Segoe UI by default) to create visual grouping—text boxes support basic HTML tags (<b>, <i>, <u>) but NOT hyperlinks or dynamic field references\n○ DELIVER:\n  • Tool: Power BI Desktop > View tab > Page view > Actual size (100% zoom) to verify visual readability at published resolution matches design intent\n  • Metric: Measure report page count and visual density—Microsoft guidance recommends ≤15 visuals per page and ≤10 report pages for optimal user experience and performance in Power BI Service\n  • Validation: Publish to Power BI Service workspace and test responsive behavior by resizing browser window from 1920px to 768px width—verify visuals reflow without horizontal scrollbars appearing (check Fit to width rendering mode)\n  • Accessibility Check: Use Windows Narrator (Win+Ctrl+Enter) to tab through report visuals—verify each visual announces meaningful Alt text (not default \"Visual title\") and tab order follows logical reading sequence (top-left to bottom-right)\n\n## 23. Slicers and Cross-Filtering Behavior\n- PREPARE:\n  • Prerequisite: Data model with dimensional tables (e.g., DimProduct, DimDate) containing categorical or hierarchical columns suitable for filtering (ProductCategory, CalendarYear, SalesRegion)\n  • Selection: Slicer visual types include List (default vertical text list) vs. Dropdown (compact single-select saving canvas space) vs. Between (numeric or date range with min/max input boxes) vs. Before/After (date filters with single boundary) vs. Relative date (last N days/months/years calculated dynamically)\n  • Execution: Drag field from Field pane to blank canvas area > automatically creates Table visual, then click Slicer icon in Visualizations pane to convert OR select Slicer visual first, then drag field to Field well\n• MODEL:\n  • **Selection Controls**: Format pane > Slicer settings > Options > Single select ON forces radio button behavior (one value only) vs. Multi-select with Ctrl (default allows multiple selections) vs. Select all checkbox (appears when Multi-select enabled, selects/deselects all items)\n  • **Search Box Configuration**: Format pane > Slicer settings > Options > Search toggle ON adds search textbox at top of slicer (filters slicer items dynamically as user types, useful for slicers with 100+ values like CustomerName)\n  • **Cross-Filtering Direction**: Slicer default behavior is unidirectional filtering (affects other visuals but not affected by them) vs. Edit interactions (Format tab) allows disabling slicer effect on specific visuals (Filter icon changes to None or Highlight)\n  • **Date Slicer Granularity**: When Calendar hierarchy column (Date datatype with Auto date/time enabled) is added to slicer, hierarchy picker appears (Year > Quarter > Month > Day) allowing drill-down filtering within slicer itself\n  • **Numeric Range Slicer**: Between slicer type for numeric columns displays two input boxes (minimum and maximum) plus optional slider bar—Format pane > Slicer settings > Range allows setting bounds (e.g., limit Price slider to $0-$10,000 even if data contains outliers)\n  • **[Critical Distinction]:** Filter pane > Filters on this page applies filter BEFORE slicer evaluation (reduces slicer available values) vs. Slicer visual filters DURING user interaction (slicers always show all available values from filtered dataset, not all data model values)\n  • **Sync Slicers**: View tab > Sync slicers pane shows matrix of report pages × slicers—check \"Sync\" column to apply same slicer selection across pages, check \"Visible\" column to display slicer on specific pages (can sync without showing)\n  • **[Design Boundary]:** Slicers with >1,000 unique values trigger warning \"This slicer might affect performance\" and switch to dropdown mode automatically—Power BI Service renders max 1,000 slicer items before pagination/search required\n  • **Hierarchy Slicer Behavior**: When field from hierarchy (e.g., Category > Subcategory > Product) added to slicer, Format pane > Slicer settings > Selection controls > Single select at each level ON enables parent selection without requiring child selection\n  • **[Exam Focus]:** Skills measured include \"Configure slicer visual types\" knowing when Relative date slicer (requires Date datatype column) is appropriate vs. List slicer (works with any column) vs. Between slicer (requires numeric or date column)\n  • **Field Parameter Slicers**: New field parameter created via Modeling tab > New parameter generates special slicer controlling WHICH measure/column appears in other visuals (e.g., \"Select Metric\" slicer switching between Sales Amount, Quantity, Profit)\n○ DELIVER:\n  • Tool: Power BI Desktop > View tab > Selection pane shows visual layer order—verify slicers appear above (later in Z-order) other visuals to prevent accidental clicking through slicer to background visual\n  • Metric: Test slicer cross-filter performance using Performance Analyzer—slicer interaction refreshing 5+ visuals should complete in <2 seconds (DAX query times + visual rendering times combined)\n  • Validation: Select value in slicer > open Filter pane > verify Filters on this page and Filters on all pages sections do NOT duplicate slicer field (indicates double-filtering misconfiguration reducing performance)\n  • Cross-Filter Check: Use Format tab > Edit interactions while slicer selected to verify cross-filter icons on all visuals—ensure critical KPI cards show Filter icon (not None) so slicer affects them, and competing slicers show None to prevent circular dependencies\n\n## 24. Drillthrough and Drill-down Navigation\n- PREPARE:\n  • Prerequisite: Data model with hierarchies (e.g., Product Category > Subcategory > Product Name) defined in Model view OR report with multiple pages where detail page contains visuals requiring filtered context from summary page\n  • Selection: Drill-down uses hierarchies within single visual (Category → Subcategory → Product expanding in same matrix/chart) vs. Drillthrough navigates between report pages passing filter context (Summary page → Detail page maintaining selected Category filter)\n  • Execution: For drill-down, create hierarchy in Model view Fields pane by dragging child field onto parent field (creates hierarchy expandable in visuals) OR drag multiple fields to visual Axis/Rows well (implicit hierarchy)\n• MODEL:\n  • **Drillthrough Configuration**: Select target detail page > Drillthrough section in Filters pane (page-level filters) > Add drillthrough fields (typically dimension attributes like ProductKey, CustomerID) that users right-click on source page to trigger navigation\n  • **Drillthrough Filter Propagation**: When drillthrough target page has additional page-level filters beyond drillthrough fields, those filters PERSIST during drillthrough (e.g., Year=2024 filter on detail page maintained even when drilling from summary page showing all years)\n  • **Back Button**: Power BI automatically adds \"Back\" button to drillthrough target pages (type = Drillthrough back button) in top-left corner—can be repositioned/formatted but NOT deleted (disabled buttons appear grayed out when navigating directly to page)\n  • **Cross-Report Drillthrough**: Requires target report in same Power BI Service workspace + both reports connected to same dataset (or source report uses \"thin\" report pattern) configured via Drillthrough settings > Cross-report > select target report from dropdown\n  • **Drill-down Visual Header Icons**: Visuals with hierarchies display header icons: Down arrow (expand one level), Double-down arrow (expand all levels), Up arrow (drill up one level)—icons appear only when hierarchy has 2+ levels\n  • **[Critical Distinction]:** Drill-down expands visual in place (matrix shows Category row, click + expands to show Subcategory rows beneath) vs. Drillthrough replaces entire page (right-click Category value → \"Drillthrough to Detail\" opens new page filtered to that Category)\n  • **Keep All Filters Option**: Drillthrough section in Filters pane > Keep all filters toggle ON passes ALL filters from source page (slicers, page filters, visual filters) to target page vs. OFF passes only drillthrough field filters (default recommended to avoid over-filtering)\n  • **[Design Boundary]:** Drillthrough cross-report requires both reports in same workspace AND same App (if published)—reports in different Apps cannot drillthrough even if datasets are shared via live connection\n  • **Measure-Based Drillthrough**: Cannot configure drillthrough on measure fields (e.g., cannot right-click Sales Amount value to drillthrough)—only dimension attribute values support drillthrough because Power BI passes attribute filter context, not measure values\n  • **Hierarchy Matrix Expand/Collapse**: Matrix visual with row hierarchy shows +/− expand buttons in row headers—Format pane > Row headers > +/− icons toggle controls visibility, Stepped layout vs. Tabular layout affects indentation rendering\n  • **[Exam Focus]:** Skills measured include \"Configure drillthrough and cross-report drillthrough\" understanding that drillthrough fields must be added to Drillthrough section (not Filters on this page) to enable right-click navigation option in source visuals\n○ DELIVER:\n  • Tool: Power BI Desktop report with drillthrough configured > right-click dimension value in visual (e.g., \"Electronics\" in Category column) > verify \"Drillthrough to [TargetPage]\" appears in context menu (if missing, check Drillthrough section on target page)\n  • Metric: Performance Analyzer measures page navigation time—drillthrough navigation to target page should load in <3 seconds (includes query refresh for all visuals on target page with new filter context)\n  • Validation: On drillthrough target page, open Filter pane > verify drillthrough field appears in Drillthrough section with active filter value (e.g., \"Category is Electronics\") and lock icon indicating it came from drillthrough action\n  • Hierarchy Check: For drill-down hierarchies in matrix visual, expand to lowest level > verify total row shows correct aggregation (sum of child rows = parent row value) ensuring hierarchy relationships defined correctly in Model view\n\n## 25. Bookmarks and Selection Pane\n- PREPARE:\n  • Prerequisite: Power BI Desktop report with multiple visuals, slicers, or page states to capture—bookmarks store visual visibility, slicer selections, filter states, focus mode, and spotlight settings at moment bookmark created\n  • Selection: Bookmarks capture Current page (default, stores state of active page only) vs. All pages (stores slicer states applying across all pages if Sync slicers enabled) determined by Bookmarks pane > More options (…) > Data checkbox settings\n  • Execution: View tab > Bookmarks pane (docked panel appears on right) > Add button creates new bookmark with auto-generated name (e.g., \"Bookmark 1\") capturing current report state—rename by double-clicking bookmark name\n• MODEL:\n  • **Bookmark Data Settings**: Each bookmark > right-click > Data checkbox ON (default) stores slicer selections, filters, and cross-filter states vs. OFF captures only visual visibility and page layout (useful for UI state bookmarks without filtering)\n  • **Display Settings**: Bookmark right-click menu > Display checkbox ON stores visual focus mode (e.g., matrix visual in focus mode expanding to full page) vs. OFF ignores focus mode in bookmark playback\n  • **Current Page Scope**: Bookmark right-click menu > Current page checkbox ON (default) applies bookmark to active page only vs. OFF makes bookmark affect all pages (typically used with All pages + Sync slicers configuration)\n  • **Selection Pane Integration**: View tab > Selection pane shows all visuals on page with eye icons (visible/hidden) and object names—use Selection pane to hide specific visuals (e.g., hide Chart 1, show Chart 2), then create bookmark to capture that visibility state\n  • **Bookmark Navigator**: Insert tab > Buttons > Navigator > Bookmark navigator creates dropdown button showing all bookmarks—users click dropdown to select bookmark for playback (alternative to individual bookmark buttons)\n  • **[Critical Distinction]:** Bookmark with Data ON captures slicer values (e.g., Year=2024) and applies those values when bookmark selected vs. Data OFF skips slicer state, leaving current user selections unchanged (useful for visual swap bookmarks)\n  • **Layering and Animation**: Selection pane allows dragging visuals up/down in list to change Z-order (layer stacking)—create two bookmarks with different Z-orders, then assign to buttons for animated transitions (e.g., swap chart positions)\n  • **[Design Boundary]:** Bookmarks do NOT capture visual-level drill state (expanded hierarchy rows in matrix, drill-down chart levels)—drill state resets to default when bookmark applied, requiring users to re-drill after bookmark navigation\n  • **Bookmark Groups**: Bookmarks pane > right-click bookmark > Group creates parent folder—nested bookmarks enable hierarchical navigation (e.g., \"Regional Analysis\" group contains \"North\", \"South\", \"East\", \"West\" bookmarks)\n  • **Spotlight Effect**: Select visual > View tab > Spotlight dims all other visuals—create bookmark while spotlight active to capture this state (right-click bookmark > Display must be ON to store spotlight effect)\n  • **[Exam Focus]:** Skills measured include \"Create bookmarks to capture report states\" understanding that bookmarks with Data ON + Display ON + Current page OFF create \"global\" bookmarks affecting entire report navigation and filtering\n  • **Update Bookmark**: After modifying visual layout or filters, select existing bookmark > Bookmarks pane > More options (…) > Update replaces bookmark with current state (does NOT create new bookmark version, overwrites existing)\n○ DELIVER:\n  • Tool: Power BI Desktop > Bookmarks pane > select bookmark > verify report state changes immediately (slicers update, visuals show/hide, filters apply) matching intended bookmark configuration\n  • Metric: Test bookmark playback sequence using Selection pane visual count—if bookmark intended to show 5 visuals but Selection pane shows 8 visible, indicates bookmark Data settings misconfigured\n  • Validation: Create bookmark > modify slicer selection > click bookmark again > verify slicer returns to bookmarked value (if Data checkbox ON) or remains at user-modified value (if Data checkbox OFF)\n  • Cross-Page Check: For bookmarks with Current page OFF, navigate to different report page > select bookmark > verify bookmark effects appear on new page (slicers update, filters apply) confirming All pages scope working correctly\n\n## 26. Buttons and Action Configuration\n- PREPARE:\n  • Prerequisite: Power BI Desktop report with target destinations for navigation (bookmarks, report pages, URLs, or Q&A) OR report with defined bookmarks for button-triggered state changes\n  • Selection: Button types include Blank (fully customizable), Back (auto-configured drillthrough return), Navigator (dropdown with bookmark/page list), or Shapes (rectangle/circle/triangle with button functionality) converted via right-click > Format as button\n  • Execution: Insert tab > Buttons dropdown > select button type (e.g., Bookmark navigator) OR Insert tab > Shapes > select shape, right-click shape > Format as button (converts static shape to interactive button)\n• MODEL:\n  • **Action Configuration**: Select button > Format pane > Action toggle ON > Type dropdown includes Page navigation (select target page), Bookmark (select target bookmark), Drill through (requires drillthrough-enabled page), Back (returns to previous page/bookmark), Web URL (external link opens new browser tab), Q&A (opens Q&A dialog)\n  • **Button Text**: Format pane > Button text toggle ON to display label—can use dynamic text via conditional formatting (fx button) referencing measure value (e.g., button shows \"Show 2024\" where 2024 comes from MAX(Sales[Year]) measure)\n  • **Icon Configuration**: Format pane > Icon toggle ON adds icon to button left of text—Icon dropdown includes 40+ built-in icons (Arrow right, Home, Back, Filter, etc.) OR Custom icon (upload .png/.jpg max 1MB)\n  • **Button States**: Format pane > Style dropdown includes Default (normal state), On Hover (mouse over), On Press (active click)—each state has independent Fill color, Border, Outline, Icon color, and Shadow settings creating visual feedback\n  • **Conditional Visibility**: Button visual > Format pane > General > Title > Fx (conditional formatting) > Field value = create DAX measure returning TRUE/FALSE to show/hide button dynamically (e.g., show \"Next Page\" button only when slicer selection = \"Active\")\n  • **Tooltip Override**: Format pane > Tooltip toggle ON shows tooltip on hover—can assign Report page tooltip (custom tooltip page) instead of default field value tooltip (useful for button help text explaining action)\n  • **[Critical Distinction]:** Bookmark buttons with Action > Type = Bookmark navigate to specific captured state vs. Page navigation buttons with Action > Type = Page navigation go to page but preserve current filters/slicers (no state reset)\n  • **Shape Button Conversion**: Shapes converted to buttons (right-click > Format as button) retain shape formatting (rounded corners, rotation, fill gradient) unlike native Button visuals which have fixed rectangular/rounded rectangle form factor\n  • **[Design Boundary]:** Button Web URL action opens links in new browser tab—cannot embed external content inline within Power BI report or configure URL to open in iframe/popup window for security reasons\n  • **Navigator Button Behavior**: Bookmark navigator button shows dropdown with all bookmarks OR Page navigator shows all pages—Format pane > Navigator > Show hidden pages toggle OFF excludes hidden pages from dropdown list\n  • **CTRL+Click Override**: While Ctrl key pressed, buttons become movable/selectable for editing instead of executing action—useful for repositioning buttons without triggering navigation during report design\n  • **[Exam Focus]:** Skills measured include \"Configure buttons to navigate report pages and bookmarks\" understanding that Action settings require Action toggle ON and Type selection before Destination dropdown populates with valid targets\n○ DELIVER:\n  • Tool: Power BI Desktop > Format pane (button selected) > Action section > verify Type dropdown shows selected action type (e.g., \"Bookmark\") and Destination dropdown shows valid target name (e.g., \"Sales Overview bookmark\")\n  • Metric: Test button hover states by positioning mouse over button—verify On Hover state activates (color changes, shadow appears) within 200ms and reverts to Default state when mouse exits button boundary\n  • Validation: Ctrl+click button in Design view to test action WITHOUT moving visual (standard click triggers action)—verify navigation/state change occurs correctly, then use Back button or Ctrl+Z to return\n  • Accessibility Check: Select button > View tab > Selection pane > verify button has descriptive Alt text (not \"Button 1\")—screen readers announce Alt text when button receives focus during keyboard navigation (Tab key)\n\n## 27. Tooltips (Standard and Report Page)\n- PREPARE:\n  • Prerequisite: For standard tooltips, visual with data fields mapped to Tooltips well in Visualizations pane—for report page tooltips, separate report page configured with canvas size = Tooltip (320x240 pixels) in Page settings\n  • Selection: Standard tooltips (default, show field name + value + aggregation) vs. Report page tooltips (custom mini-report page rendered in tooltip on hover showing multiple visuals, charts, cards) vs. Tooltip OFF (disables hover tooltip completely)\n  • Execution: For standard tooltip, drag additional fields from Field pane to Tooltips well in visual (fields appear in tooltip but NOT in visual itself) OR for report page tooltip, create new page > Page settings > Canvas size = Tooltip, then select source visual > Format pane > Tooltip > Page = select tooltip page\n• MODEL:\n  • **Report Page Tooltip Configuration**: Create tooltip page (320x240 canvas) with visuals, then source visual > Format pane > General > Tooltip toggle ON > Type = Report page (vs. Default) > Page dropdown = select tooltip page name\n  • **Tooltip Filter Context**: When report page tooltip appears on hover over visual data point, Power BI automatically passes filter context from hovered data point to tooltip page (e.g., hover over \"Electronics\" bar → tooltip page filters to Category = Electronics)\n  • **Tooltip Field Assignment**: To control which field(s) pass to tooltip page, tooltip page > Drillthrough section in Filter pane > add fields as drillthrough fields—these fields must exist in source visual for tooltip to activate (if source visual lacks drillthrough field, tooltip shows \"No data\")\n  • **Standard Tooltip Fields**: In source visual Tooltips well, drag measure/column fields—Format pane > Tooltip > Display units, Decimal places, Font size, Background color controls tooltip appearance (applies to standard tooltips only, NOT report page tooltips)\n  • **Tooltip Delay**: Format pane > Tooltip > Show delay slider (0-5000ms) controls how long mouse must hover before tooltip appears (default 300ms)—increase delay for dense visuals where accidental hovers cause distraction\n  • **[Critical Distinction]:** Standard tooltips show only field values from Tooltips well (static aggregations like SUM, AVERAGE) vs. Report page tooltips execute full DAX measures and visuals with drill-down, allowing dynamic calculations like running totals, % change, conditional formatting\n  • **Canvas Size Enforcement**: Tooltip page MUST have Canvas size = Tooltip (320x240) in Page settings—if canvas size is 16:9 or Custom, tooltip option becomes unavailable in source visual Format pane (grayed out or missing)\n  • **[Design Boundary]:** Report page tooltips do NOT support user interaction—cannot click buttons, select slicer values, or drill visuals within tooltip (tooltip dismisses on mouse movement away from source data point)\n  • **Multiple Tooltip Pages**: Create multiple tooltip pages (e.g., \"Product Tooltip\", \"Customer Tooltip\", \"Sales Tooltip\") then assign different tooltip pages to different visuals on same report page via Format pane > Tooltip > Page dropdown\n  • **Tooltip with Measures**: Add measure to Tooltips well (e.g., Profit Margin % = DIVIDE([Profit], [Sales])) shows calculated value in tooltip without displaying in visual itself—useful for supplementary metrics not fitting in visual layout\n  • **Conditional Tooltip Text**: Standard tooltip field values support conditional formatting via fx button in Tooltips well—can change tooltip text color based on value (e.g., red text if Sales < 0, green if >= 0)\n  • **[Exam Focus]:** Skills measured include \"Design report page tooltips\" understanding canvas size requirement (320x240 Tooltip type), drillthrough field configuration for filter context passing, and limitation that tooltips cannot have interactive elements\n○ DELIVER:\n  • Tool: Power BI Desktop > hover mouse over visual data point (e.g., bar in bar chart, cell in matrix) > verify tooltip appears within 300-500ms showing expected fields/visuals\n  • Metric: For report page tooltips, measure tooltip load time using Performance Analyzer—tooltip page should render in <1 second (includes DAX query execution for all visuals on tooltip page filtered to hovered data point context)\n  • Validation: Hover over different data points in source visual (e.g., different bars in chart) > verify tooltip content changes reflecting filter context (e.g., Product = \"Laptop\" shows Laptop sales in tooltip, Product = \"Phone\" shows Phone sales)\n  • Tooltip Page Check: Select tooltip page in Pages pane > Page settings > verify Canvas size shows \"Tooltip\" (not 16:9 or Custom)—if wrong canvas size, tooltip will not appear when hovering over source visuals on other pages\n\n## 28. Conditional Formatting\n- PREPARE:\n  • Prerequisite: Visual with measure or column field that supports conditional formatting (table/matrix cells, KPI card backgrounds, data bars, icon sets)—not all visual types support conditional formatting (line chart does NOT support background color rules, only data colors)\n  • Selection: Conditional formatting types include Background color (cell/card fill), Font color (text color), Data bars (horizontal bars in table cells scaled to values), Icons (traffic lights, arrows, flags based on thresholds), Web URL (clickable hyperlinks)\n  • Execution: Select visual > Visualizations pane > expand field in Values well > click fx icon (conditional formatting) next to field name > select formatting type from menu (Background color, Font color, Data bars, Icons, Web URL)\n• MODEL:\n  • **Rules-Based Formatting**: Conditional formatting dialog > Format style = Rules > define IF rules (e.g., if value >= 1000000 then Green, if value >= 500000 then Yellow, else Red)—supports up to 10 rules evaluated top-to-bottom\n  • **Field Value Formatting**: Format style = Field value references measure returning color name (\"Red\", \"Green\", \"#FF6600\" hex code) OR number for gradient scale—useful for dynamic colors based on complex DAX logic (e.g., color based on % to target calculation)\n  • **Gradient Formatting**: Format style = Gradient creates color scale with Minimum (red default), Center (optional yellow), Maximum (green default)—can set based on Lowest/Highest value, Number, Percent, or Percentile\n  • **Data Bars Configuration**: Conditional formatting > Data bars > Show bar only checkbox hides number value, displays only bar (useful for visual-only column like sparklines)—Positive bar color, Negative bar color, and Axis color configurable separately\n  • **Icon Sets**: Conditional formatting > Icons > Icon layout = Left/Right of value (icon appears before/after number) vs. Placeholder (icon only, no number)—Icon style includes 3-icon, 4-icon, 5-icon sets (arrows, flags, traffic lights, stars)\n  • **[Critical Distinction]:** Background color conditional formatting applies to entire cell/card vs. Data bars render within cell leaving margin space vs. Icons appear as small graphic adjacent to value—cannot combine all three in same cell (choose one formatting type per field)\n  • **Summarization Context**: When field in Values well uses aggregation (SUM, AVERAGE), conditional formatting evaluates AFTER aggregation—cannot format \"red if individual transaction > $1000\" in table showing SUM(Sales) grouped by Month (formats based on monthly total, not individual rows)\n  • **[Design Boundary]:** Conditional formatting on matrix visuals applies to Values only—cannot apply background color to Row headers or Column headers (those areas remain white/default theme color)\n  • **Web URL Formatting**: Conditional formatting > Web URL > Field value = select column containing URLs (must be full http:// or https:// URLs)—table cell displays underlined hyperlink text (can customize Display text vs. URL destination using separate fields)\n  • **Measure-Based Rules**: Create DAX measure returning color value, e.g., `Status Color = IF([Sales] >= 1000000, \"Green\", \"Red\")`, then use Field value formatting referencing this measure—enables complex multi-condition logic beyond 10-rule limit\n  • **Format by Another Field**: Rules-based formatting > Based on field dropdown allows selecting different field for condition vs. formatted field (e.g., format Sales background color based on Profit Margin % value from different column)\n  • **[Exam Focus]:** Skills measured include \"Apply conditional formatting to visualizations\" understanding that fx icon appears only for fields supporting formatting (Values/Columns in table/matrix, not Rows) and Format style options vary by visual type\n○ DELIVER:\n  • Tool: Power BI Desktop > select table/matrix visual with conditional formatting applied > verify fx icon appears next to formatted field in Values well (purple fx icon indicates active conditional formatting)\n  • Metric: Test conditional formatting rules by modifying underlying data (e.g., change measure filter, adjust slicer) > verify cell colors/icons update within 1 second reflecting new calculated values meeting rule thresholds\n  • Validation: For gradient formatting, verify color scale spans correctly—Minimum value should show darkest color (e.g., red), Maximum value should show brightest color (e.g., green), with smooth gradient between (not abrupt color jumps)\n  • Accessibility Check: Avoid using ONLY color to convey information (e.g., red=bad, green=good)—supplement with Icons or Data bars so colorblind users can distinguish values (WCAG 2.1 requirement: \"Color is not used as the only visual means of conveying information\")\n\n## 29. Dashboard Creation from Reports\n- PREPARE:\n  • Prerequisite: Power BI Service account with workspace access (Contributor or higher role) + published report (.pbix) in workspace—dashboards exist ONLY in Power BI Service, NOT in Power BI Desktop\n  • Selection: Create dashboard from scratch (pin first visual/tile) vs. use existing dashboard (pin additional tiles to existing dashboard) vs. create from Q&A (type natural language query, pin result visual as tile)\n  • Execution: In Power BI Service, open report > hover over visual > pin icon (upper-right corner of visual) > Pin to dashboard dialog > New dashboard radio button > enter dashboard name > Pin button\n• MODEL:\n  • **Pin Live Page**: Report page upper-right corner > ellipsis (…) > Pin to a dashboard > Pin live page option creates single tile showing entire report page—tile updates dynamically when report page changes (vs. pinning individual visuals creates static snapshot tiles)\n  • **Dashboard Tile Properties**: After pinning, click tile ellipsis (…) > Edit details > configure Title, Subtitle, Display last refresh time toggle, Set custom link (URL or other dashboard/report) for click-through navigation\n  • **Tile Refresh Behavior**: Tiles pinned from DirectQuery reports refresh automatically when dashboard loaded vs. Tiles from Import mode reports show data from last dataset refresh (check dataset Settings > Scheduled refresh for Import mode)\n  • **Real-Time Tiles**: Pin streaming dataset tile (created from real-time API or Azure Stream Analytics) to dashboard—tile updates every few seconds without manual refresh (shows web traffic, IoT sensor data, stock prices)\n  • **Q&A Tile Creation**: Dashboard upper menu > Ask a question about your data (Q&A box) > type natural language query (e.g., \"total sales by category\") > Q&A generates visual > pin icon to save as dashboard tile\n  • **[Critical Distinction]:** Dashboard tiles are READ-ONLY snapshots showing data at last refresh vs. Report visuals are interactive allowing drill, filter, cross-highlight—dashboard click-through opens underlying report in interactive mode\n  • **Tile Arrangement**: Drag tiles to reposition, drag corner handles to resize—dashboard uses grid layout (tiles snap to grid intersections), maximum dashboard size = 10 columns wide × unlimited rows (mobile dashboard layout is separate 2-column phone view)\n  • **[Design Boundary]:** Dashboards do NOT support slicers—filtering must occur in underlying reports before pinning tiles OR use dashboard-level filters (Q&A natural language filter like \"show sales for 2024\") which does NOT persist across sessions\n  • **Theme and Appearance**: Dashboard settings (gear icon) > Dashboard theme applies color scheme to dashboard background—does NOT change tile visual colors (those inherit from report theme at time of pinning)\n  • **Alert Configuration**: Numeric KPI tiles (single value card pinned from report) > tile ellipsis (…) > Manage alerts > set threshold (e.g., notify me when Sales > 1000000)—alerts send email/mobile notification when threshold crossed, checked every 15-60 minutes depending on dataset\n  • **Dashboard Comments**: Tile or dashboard > Comments icon (speech bubble) adds comment thread—useful for collaboration (e.g., \"Why did sales drop in Q3?\") with @mention notifications to workspace members\n  • **[Exam Focus]:** Skills measured include \"Pin visuals from reports to dashboards\" understanding that pinning creates one-way snapshot (report changes do NOT auto-update tile unless Pin live page used) and dashboard tiles link back to source report for interactivity\n○ DELIVER:\n  • Tool: Power BI Service > Dashboard > tile ellipsis (…) > View details shows tile lineage (source report, page, visual) and last refresh timestamp—verify timestamp matches dataset refresh schedule\n  • Metric: Dashboard load time should be <3 seconds for 20 tiles—if slower, check tile query performance using Performance Analyzer on source reports (optimize slow DAX measures before pinning)\n  • Validation: Pin visual from report to dashboard > open dashboard > verify tile displays correctly and matches report visual appearance—click tile to verify navigation returns to correct report page and visual context\n  • Mobile Dashboard Check: Power BI Service > Dashboard > Web view shows desktop layout—switch to Phone view (dashboard settings) to arrange tiles in 2-column mobile layout (separate from desktop layout, manually configured)\n\n## 30. Dashboard Tiles and Q&A\n- PREPARE:\n  • Prerequisite: Power BI Service dashboard with at least one tile OR dataset with Q&A enabled (natural language query feature) in workspace—Q&A requires Import or DirectQuery mode (Live connection to SSAS does NOT support Q&A)\n  • Selection: Tile types include Pinned visual (from report), Pinned live page (entire report page), Q&A tile (created from natural language query), Custom streaming tile (real-time data), Web content tile (embed external URL/image), Text box tile (markdown-formatted text)\n  • Execution: Dashboard > Add tile button (upper menu) > opens Add tile dialog with tile type options—select Web content to embed iframe, Text box to add markdown, or use dashboard Q&A box for natural language tile creation\n• MODEL:\n  • **Q&A Natural Language Syntax**: Dashboard Q&A box supports queries like \"total sales by year\" (aggregation), \"top 10 products by revenue\" (ranking), \"sales last month\" (time intelligence), \"show as map\" (visualization type specification)\n  • **Q&A Suggestions**: Start typing in Q&A box > dropdown shows suggested questions based on dataset schema—clicking suggestion auto-completes query and generates visual (e.g., \"What were the total sales?\" suggestion appears when typing \"sales\")\n  • **Q&A Synonyms**: Dataset settings > Q&A and Cortana > Teach Q&A section allows defining synonyms (e.g., \"revenue\" = \"sales\", \"goods\" = \"products\") improving Q&A understanding—synonyms apply to specific table/column names\n  • **Featured Questions**: Dataset settings > Featured questions section allows creating curated Q&A questions displayed to users as clickable suggestions in Q&A box—useful for guiding users to important metrics (e.g., \"What is year-over-year growth?\")\n  • **Q&A Visual Conversion**: After Q&A generates visual result, Visualization pane appears on right allowing changing chart type (bar chart → line chart), adding fields, applying filters—click Pin visual to save Q&A result as dashboard tile\n  • **[Critical Distinction]:** Q&A tiles are STATIC snapshots of query result at creation time vs. Report visuals pinned as tiles are LIVE (reflect underlying dataset refresh)—Q&A tiles require manual re-query and re-pin to update with new data\n  • **Web Content Tile Configuration**: Add tile > Web content > paste URL or embed code—supports iframe embedding (external website), direct image URL (.png/.jpg), or YouTube video embed code (generates video player tile)\n  • **Text Box Tile Markdown**: Add tile > Text box > supports markdown syntax (# headers, **bold**, [links](url), bullet lists) for formatted text—useful for dashboard instructions, data source disclaimers, last updated notes\n  • **[Design Boundary]:** Dashboard tiles maximum size = 10 columns × 10 rows (tiles cannot exceed these dimensions)—attempting larger resize snaps tile back to max size (10×10 grid squares)\n  • **Tile Click-Through Behavior**: Tile ellipsis (…) > Edit details > Custom link section allows overriding default click-through destination—instead of opening source report, can navigate to external URL, different report, or another dashboard\n  • **Tile Refresh Management**: Import mode tiles show timestamp \"Data refreshed at [time]\" based on dataset refresh schedule—DirectQuery tiles show \"Data refreshed when dashboard loaded\" (live query on each view)\n  • **Q&A Language Support**: Q&A supports English, Spanish, French, German, Japanese, Chinese (Simplified)—language detected from dataset locale setting in Power BI Desktop (File > Options > Regional settings)\n  • **[Exam Focus]:** Skills measured include \"Use Q&A to create dashboard tiles\" understanding Q&A requires careful dataset field naming (no abbreviations, spaces vs. underscores), synonyms configuration, and featured questions for user guidance\n○ DELIVER:\n  • Tool: Power BI Service > Dashboard Q&A box > type test query (e.g., \"total sales\") > verify Q&A interprets query correctly (shows \"Sum of Sales\" visual, not error message \"I didn't understand that\")\n  • Metric: Q&A query response time should be <2 seconds for simple aggregations (e.g., \"sum of sales\"), <5 seconds for complex queries with multiple filters/groupings—longer times indicate dataset model optimization needed\n  • Validation: Create Q&A tile from query > pin to dashboard > verify tile displays correctly—compare tile values to source report visual values confirming Q&A interpreted query correctly (same numbers = correct interpretation)\n  • Synonym Test: Dataset settings > Q&A and Cortana > Add synonym (e.g., \"revenue\" for \"Sales Amount\" field) > return to dashboard Q&A > type \"total revenue\" > verify Q&A recognizes synonym and generates \"Sum of Sales Amount\" visual (not error message)\n```\n\n```\n## 31. Mobile Layout Optimization\n- PREPARE:\n  • Prerequisite: Power BI Desktop (minimum version 2.95) with published .pbix report to Power BI Service workspace\n  • Selection: Mobile Layout view in Power BI Desktop (View tab > Mobile Layout) vs. responsive visuals that auto-resize vs. fixed-size desktop-only layout\n  • Execution: Open .pbix file > View tab > Click \"Mobile Layout\" toggle > Canvas changes to 9:16 portrait orientation (720x1280px)\n• MODEL:\n  • Canvas Size: 720px width × 1280px height (iPhone 13 Pro standard)\n  • Visual Placement: Drag visuals from Fields pane on right to mobile canvas (desktop visuals remain independent)\n  • Touch Target Sizing: Minimum 44x44 pixels per iOS Human Interface Guidelines (buttons, slicers, filters)\n  • Slicer Optimization: Use Dropdown slicer style instead of List (takes less vertical space)\n  • Conditional Formatting: Apply mobile-specific color scales (higher contrast for outdoor viewing)\n  • Navigation: Add Bookmarks with mobile-friendly navigation buttons (minimum 60px height)\n  • Visual Hierarchy: Place KPI cards at top 200px, charts in middle, tables at bottom (thumb-reachable zones)\n  • **[Critical Distinction]:** Mobile Layout creates separate canvas vs. Responsive Visuals that resize automatically (Mobile Layout gives precise control over mobile experience)\n  • **[Design Boundary]:** Mobile Layout does NOT support custom visuals requiring mouse hover interactions (tooltips limited to tap-and-hold)\n  • **[Exam Focus]:** PL-300 Objective 4.2 - \"Design and configure mobile-optimized reports\" tests ability to create distinct mobile layouts with appropriate visual sizing\n○ DELIVER:\n  • Tool: Power BI Mobile app (iOS/Android) or Power BI Service mobile browser view\n  • Metric: Visual load time < 3 seconds on 4G connection (check in Performance Analyzer before publishing)\n  • Validation: Test on actual device at powerbi.com > Navigate to report > Verify all visuals visible without horizontal scrolling, slicer dropdowns functional, touch targets ≥ 44px\n\n## 32. Paginated Reports (SSRS-style)\n- PREPARE:\n  • Prerequisite: Power BI Report Builder (free download from Microsoft, separate from Power BI Desktop) AND Power BI Premium Per User (PPU) or Premium capacity for publishing\n  • Selection: Power BI Report Builder (.rdl files) for pixel-perfect printing vs. Power BI Desktop (.pbix) for interactive dashboards vs. Excel (.xlsx) for ad-hoc tabular reports\n  • Execution: Download Report Builder from Power BI Service > Apps > Get apps > Search \"Power BI Report Builder\" > Install > Launch > File > New > Blank Report\n• MODEL:\n  • Data Source: Create Embedded Connection to Power BI dataset using \"Power BI dataset\" connection type (or SQL Server using \"Microsoft SQL Server\" connection)\n  • Dataset Query: Use DAX query in dataset properties (e.g., `EVALUATE 'Sales'` for table, or `EVALUATE SUMMARIZECOLUMNS('Date'[Year], \"Total\", [Total Sales])` for aggregated data)\n  • Page Settings: A4 (8.27 × 11.69 inches) or Letter (8.5 × 11 inches) with 0.5-inch margins (Page Setup > Page Properties)\n  • Table/Matrix: Insert > Table from ribbon, bind to dataset fields, enable \"Repeat header rows on each page\" for multi-page reports\n  • Parameters: Report Data pane > Right-click Parameters > Add Parameter > Set Available Values from dataset query (e.g., `SELECT DISTINCT [Category] FROM Products`)\n  • Expressions: Use Visual Basic expressions `=Fields!Quantity.Value * Fields!Price.Value` for calculated columns (not DAX in paginated reports)\n  • Grouping: Right-click table row > Add Group > Parent Group > Group by [Category] field, add `=Sum(Fields!Sales.Value)` in group footer\n  • **[Critical Distinction]:** Paginated Reports use .rdl (Report Definition Language) format with row-by-row rendering vs. .pbix files use columnar in-memory model (paginated = SSRS engine, Power BI = VertiPaq engine)\n  • **[Design Boundary]:** Paginated Reports do NOT support custom Power BI visuals, AI visuals, or cross-filtering interactions (designed for static, print-ready output)\n  • **[Exam Focus]:** PL-300 Objective 4.4 - \"Design report layouts for paginated reports\" tests understanding when to use paginated vs. interactive reports\n○ DELIVER:\n  • Tool: Power BI Report Builder > Home tab > Run button (or Ctrl+R) to preview report locally\n  • Metric: Page break accuracy (verify group breaks occur correctly), print preview matches screen preview\n  • Validation: File > Publish to Power BI Service (requires PPU/Premium workspace) > Download as PDF and verify formatting, page numbers, headers/footers render correctly\n\n## 33. Power BI Apps for Distribution\n- PREPARE:\n  • Prerequisite: Power BI Pro license (minimum) for creator, Power BI Service workspace with Admin or Member role, published reports/dashboards in that workspace\n  • Selection: Power BI App (curated collection with simplified navigation) vs. Workspace Sharing (full edit access) vs. Email Subscription (static snapshots) for end-user distribution\n  • Execution: Power BI Service > Select workspace > Top-right \"Create app\" button (or Workspace settings > App > Create app)\n• MODEL:\n  • App Name: Unique name (e.g., \"Sales Analytics Q4\") displayed in Apps list for end users\n  • Content Selection: Choose which reports/dashboards to include from workspace (Setup tab > Add content > Select reports, uncheck \"Include in app\" for draft items)\n  • Navigation Builder: Create custom navigation (Navigation tab > New section > Add reports) with sections like \"Overview\", \"Details\", \"Admin\" (max 3 levels deep)\n  • App Audience: Add security groups or individual emails in Access tab (users only need Power BI Free license to view if workspace is in Premium capacity)\n  • Permissions: Set \"Build permission\" to allow users to create reports on underlying datasets (Permissions tab > Allow users to connect to underlying datasets)\n  • App Logo: Upload 240x240 PNG logo (App settings > Logo > Upload image)\n  • App Description: Add Markdown-formatted description with links (Support tab > Description field supports **bold**, [links](URL))\n  • **[Critical Distinction]:** Power BI Apps provide read-only curated experience vs. Workspace access gives content editing rights (Apps = consumption-focused, Workspaces = collaboration-focused)\n  • **[Design Boundary]:** Apps do NOT support dynamic role-based navigation or conditional section visibility (all users see same navigation structure, RLS filters data not UI)\n  • **[Exam Focus]:** PL-300 Objective 4.3 - \"Manage workspaces and apps\" tests ability to create apps with appropriate permissions and navigation\n○ DELIVER:\n  • Tool: Power BI Service > Workspace > Click \"Create app\" > Fill settings > Click \"Publish app\" button (orange button top-right)\n  • Metric: User adoption tracking (Workspace settings > Usage metrics > App views, active users count)\n  • Validation: Log in as test user (or use incognito with test account) > Apps section > Verify app appears, navigation works, reports load, RLS applies correctly\n\n## 34. Workspace Roles and Permissions\n- PREPARE:\n  • Prerequisite: Power BI Service account with Admin role on target workspace, Azure AD group (optional but recommended for scalable permission management)\n  • Selection: Workspace Roles (Admin/Member/Contributor/Viewer) vs. App Permissions (read-only with optional Build) vs. Item-level Sharing (specific report/dashboard sharing)\n  • Execution: Power BI Service > Workspaces > Select workspace > Access button (top ribbon) > Add user or group email\n• MODEL:\n  • Admin Role: Full control - manage workspace settings, delete workspace, assign roles, create/update/delete all content, publish apps\n  • Member Role: Create/edit/delete content in workspace, publish apps, manage dataset permissions, CANNOT delete workspace or change workspace-level settings\n  • Contributor Role: Create/edit content, publish reports, CANNOT delete others' content, CANNOT publish apps or manage dataset permissions\n  • Viewer Role: Read-only access to all workspace content (even unpublished items), useful for auditors or stakeholders who need visibility without editing\n  • Build Permission: Separate from roles - allows users to create new reports using workspace datasets (managed at dataset level > Settings > Build permission)\n  • **[Critical Distinction]:** Workspace roles control workspace-level actions vs. Dataset Build permission controls who can connect to datasets vs. App permissions control end-user viewing (three separate permission layers)\n  • **[Design Boundary]:** Viewer role provides access to ALL workspace content including drafts (no way to hide specific items from Viewers in workspace, must use Apps for filtered content exposure)\n  • **[Exam Focus]:** PL-300 Objective 1.5 - \"Manage workspaces and datasets\" tests understanding of role hierarchy and when to use each role type\n○ DELIVER:\n  • Tool: Power BI Service > Workspace > Access > Review current assignments and role distribution\n  • Metric: Principle of least privilege - verify users have minimum role needed (e.g., analysts as Contributors not Members, business users get App access not workspace access)\n  • Validation: Test with secondary account or ask colleague to verify: Login as Member > Attempt to delete workspace (should fail), Login as Viewer > Attempt to edit report (should fail)\n\n## 35. Deployment Pipelines (Dev/Test/Prod)\n- PREPARE:\n  • Prerequisite: Power BI Premium Per User (PPU), Premium capacity (P SKU), or Embedded capacity (A/EM SKU) - NOT available with Pro-only licenses\n  • Selection: Deployment Pipelines (automated Dev>Test>Prod promotion) vs. Manual workspace copying vs. Azure DevOps with Power BI REST API for custom CI/CD\n  • Execution: Power BI Service > Deployment pipelines (left nav) > Create pipeline button > Name pipeline \"Sales Analytics Pipeline\" > Assign workspaces to stages\n• MODEL:\n  • Pipeline Stages: Development (build/test changes) > Test (UAT and validation) > Production (end-user consumption) - three-stage linear flow\n  • Workspace Assignment: Assign existing workspaces to stages (or create new ones) - one workspace per stage (e.g., \"Sales Dev\", \"Sales Test\", \"Sales Prod\")\n  • Deployment: Select content from source stage > Deploy button > Choose items (reports, dashboards, datasets, dataflows) > Deployment copies content to next stage\n  • Parameter Rules: Create deployment rules to change dataset connection strings per environment (e.g., Dev points to dev SQL server, Prod points to prod SQL server)\n  • Incremental Deployment: Automatic incremental refresh policies and aggregations carry over during deployment without full dataset refresh\n  • Automation: Use Power BI REST API `POST https://api.powerbi.com/v1.0/myorg/pipelines/{pipelineId}/deploy` for automated deployments from Azure DevOps pipeline\n  • **[Critical Distinction]:** Deployment Pipelines copy content with metadata vs. Azure DevOps integration with .pbix file versioning in Git (Pipelines = GUI-driven deployment, DevOps = code-based versioning)\n  • **[Design Boundary]:** Deployment Pipelines do NOT support branching or rollback (linear progression only, must manually restore previous version from .pbix backup)\n  • **[Exam Focus]:** PL-300 Objective 1.4 - \"Implement and manage a Power BI environment\" tests understanding of deployment strategies and Premium features\n○ DELIVER:\n  • Tool: Deployment Pipelines interface > Compare stages button shows differences between Dev/Test/Prod (modified reports highlighted in orange)\n  • Metric: Deployment success rate, time from Dev to Prod (track in audit logs), number of post-deployment issues reported\n  • Validation: After deployment > Navigate to Prod workspace > Open deployed report > Verify data connections work (check Last refresh time), test RLS rules, validate parameter rules applied correctly\n\n## 36. Dataset Endorsement (Certified/Promoted)\n- PREPARE:\n  • Prerequisite: Power BI Pro license, published dataset in Power BI Service workspace, tenant admin must enable endorsement feature (Admin portal > Tenant settings > Endorsement)\n  • Selection: Certified (admin-approved, enterprise-grade) vs. Promoted (creator-endorsed, team-level) vs. No endorsement (default state) for dataset quality signaling\n  • Execution: Power BI Service > Workspace > Dataset (three dots) > Settings > Endorsement section > Select Promoted or request Certification\n• MODEL:\n  • Promoted Badge: Dataset owner can self-promote (Settings > Endorsement > Promoted) to indicate \"ready for team use\" - green checkmark icon in workspace\n  • Certified Badge: Requires Certification permission granted by tenant admin (Admin portal > Endorsement settings > Specific users can certify datasets) - gold medal icon\n  • Certification Process: Dataset owner submits request > Certifier reviews data quality, documentation, refresh schedule > Approves via Settings > Endorsement > Certified > Provide certification details URL\n  • Discoverability: Endorsed datasets appear higher in Get Data search results, filters available (Get Data > Power BI datasets > Filter: Certified/Promoted)\n  • Description Requirement: Add detailed dataset description (Settings > Description) with data sources, refresh schedule, contact owner - required for certification best practice\n  • **[Critical Distinction]:** Certified = admin-approved with formal review process vs. Promoted = self-service endorsement (Certified signals enterprise governance, Promoted signals team validation)\n  • **[Design Boundary]:** Endorsement does NOT restrict access or usage (purely informational badge, must use workspace roles/RLS for access control)\n  • **[Exam Focus]:** PL-300 Objective 1.5 - \"Configure dataset endorsement\" tests understanding of governance features and when to use Certified vs. Promoted\n○ DELIVER:\n  • Tool: Power BI Service > Browse datasets > Filter by Certified to verify badge displays correctly\n  • Metric: Percentage of production datasets Certified (governance KPI), user adoption of Certified datasets vs. uncertified (check dataset usage metrics)\n  • Validation: Get Data > Power BI datasets > Search for endorsed dataset > Verify badge shows, hover over badge shows certification details and certifier name\n\n## 37. Gateway Configuration for On-Premises Data\n- PREPARE:\n  • Prerequisite: On-premises data gateway (standard mode, not personal mode) installed on Windows Server (minimum 8GB RAM, 8-core CPU recommended), domain-joined machine with .NET Framework 4.7.2+\n  • Selection: On-premises data gateway (standard mode for organization-wide use) vs. Personal gateway (single-user, limited features) vs. VPN + Direct Query (alternative for cloud-hosted VMs)\n  • Execution: Download gateway from powerbi.com > Settings > Manage gateways > Install on server > Sign in with Power BI account > Register gateway with unique name\n• MODEL:\n  • Gateway Registration: Name gateway (e.g., \"PROD-SQL-Gateway-East\"), create recovery key (store securely - required for migration/recovery)\n  • Data Source Configuration: Manage gateways page > Add data source > Select type (SQL Server, Oracle, SharePoint on-prem) > Enter server name, database name\n  • Credentials: Choose authentication method (Windows, Basic, OAuth2) > Enter credentials (gateway encrypts and stores locally) > Credentials used for scheduled refresh\n  • Gateway Cluster: Add additional gateway members for high availability (Manage gateways > Add member to cluster) - automatic failover if primary gateway offline\n  • Query Caching: Enable caching for DirectQuery (data source settings > Advanced > Cache queries for up to 24 hours) - reduces load on on-prem database\n  • User Permissions: Grant dataset owners \"Use\" permission on gateway data source (data source > Users tab > Add users) - allows them to schedule refresh\n  • Monitoring: Use gateway performance logs (gateway install folder > GatewayInfo.log) and Power BI Admin portal > Capacity metrics > Gateway performance\n  • **[Critical Distinction]:** Standard gateway supports scheduled refresh AND DirectQuery vs. Personal gateway supports scheduled refresh ONLY (personal cannot handle real-time DirectQuery connections)\n  • **[Design Boundary]:** Gateway does NOT support all Power BI data sources (e.g., Web API with OAuth requires Power BI Service credentials, cannot use gateway)\n  • **[Exam Focus]:** PL-300 Objective 1.1 - \"Configure data source connections and gateway settings\" tests ability to set up gateway for enterprise scenarios\n○ DELIVER:\n  • Tool: Power BI Service > Manage gateways > Select gateway > Connection test button (validates network connectivity to gateway machine)\n  • Metric: Gateway query performance (Admin portal > On-premises data gateway page shows query duration percentiles), gateway uptime percentage\n  • Validation: Create test dataset with on-prem data source > Schedule refresh > Check refresh history (dataset settings > Refresh history) > Verify \"Completed\" status and timestamp within expected range\n\n## 38. Dataflows for Self-Service ETL\n- PREPARE:\n  • Prerequisite: Power BI Pro license (for workspace with dataflows enabled), Premium capacity or PPU (for computed entities and incremental refresh in dataflows)\n  • Selection: Dataflows (reusable ETL in Power BI Service) vs. Power Query in Power BI Desktop (single-use transformations) vs. Azure Data Factory (enterprise data engineering)\n  • Execution: Power BI Service > Workspace > New > Dataflow > Define new entities or link entities > Name dataflow \"Customer Master Dataflow\"\n• MODEL:\n  • Entity Creation: Add tables from data sources (Get data > SQL Server, SharePoint, etc.) > Apply Power Query M transformations in browser-based editor\n  • Computed Entities: Create derived entities referencing other entities within dataflow (e.g., `= Sales[Amount] * 1.1` for tax calculation) - requires Premium capacity\n  • Linked Entities: Reference entities from other dataflows in same workspace (New entity > Link to entity) - promotes reusability across dataflows\n  • Incremental Refresh: Configure on entity (Entity settings > Incremental refresh > Define date column and archive/refresh ranges) - e.g., refresh last 30 days, archive 5 years\n  • Storage Location: Choose Azure Data Lake Storage Gen2 for dataflow storage (Workspace settings > Azure connections) - enables advanced analytics with Spark/Databricks\n  • Scheduled Refresh: Set refresh schedule (Dataflow settings > Scheduled refresh > Up to 48 times per day with Premium/PPU)\n  • Enhanced Compute Engine: Enable for computed entities (Dataflow settings > Enhanced compute engine settings > On) - optimizes query performance with intelligent caching\n  • **[Critical Distinction]:** Dataflows store transformed data in CDM (Common Data Model) format vs. Power Query in Desktop stores transforms in .pbix file only (Dataflows enable shared ETL logic across multiple datasets)\n  • **[Design Boundary]:** Dataflows do NOT support real-time streaming or DirectQuery (batch refresh only, minimum 15-minute refresh interval even with Premium)\n  • **[Exam Focus]:** PL-300 Objective 1.2 - \"Create and manage dataflows\" tests understanding of when to use dataflows vs. dataset-level transformations\n○ DELIVER:\n  • Tool: Dataflow settings > Refresh history shows success/failure status, duration, row counts processed per entity\n  • Metric: Dataflow refresh duration (should complete within allocated capacity timeframe), entity row counts match source expectations\n  • Validation: Create test dataset > Get data > Dataflows > Select entity from dataflow > Verify data loads correctly, transformations applied, refresh timestamp current\n\n## 39. Incremental Refresh Policy\n- PREPARE:\n  • Prerequisite: Power BI Premium capacity, PPU, or Embedded capacity (NOT available with Pro-only), dataset with DateTime column for filtering (e.g., OrderDate, TransactionDate)\n  • Selection: Incremental Refresh (loads only new/changed data) vs. Full Refresh (reloads entire table every time) vs. Composite Model with mixed modes (some tables incremental, others full)\n  • Execution: Power BI Desktop > Manage Parameters > Create RangeStart and RangeEnd DateTime parameters > Filter table using these parameters > Publish > Configure policy in Service\n• MODEL:\n  • Parameter Creation: Home > Manage Parameters > New > RangeStart (Type: Date/Time, Current Value: 1/1/2020) and RangeEnd (Type: Date/Time, Current Value: 1/1/2025) - case-sensitive names required\n  • Filter Application: Power Query > Select Date column > Filter > Date/Time Filters > Custom Filter > `[Date] >= RangeStart and [Date] < RangeEnd`\n  • Policy Configuration: Publish to Service > Dataset settings > Incremental refresh > Turn on > Set Archive data starting (e.g., 5 years) and Refresh data starting (e.g., 10 days before current date)\n  • Detect Data Changes: Enable \"Get the latest data in real time with DirectQuery (Premium only)\" checkbox - creates hybrid model with historical Import and recent DirectQuery\n  • Only Refresh Complete Days: Check this option to avoid partial-day refreshes (waits until day is complete based on timezone)\n  • Initial Refresh: First refresh loads all historical data within archive window, subsequent refreshes load only incremental range\n  • Partitioning: Service automatically creates partitions behind scenes (one per day for refresh window, monthly/yearly for archive) - managed transparently\n  • **[Critical Distinction]:** Incremental Refresh with DirectQuery (hybrid) provides real-time recent data vs. Incremental Refresh only (all Import mode) optimizes refresh speed but has data latency\n  • **[Design Boundary]:** Incremental Refresh does NOT work with tables using Table.Buffer() in M code or non-deterministic functions (prevents query folding required for partitioning)\n  • **[Exam Focus]:** PL-300 Objective 2.3 - \"Configure incremental refresh\" tests ability to set up parameters correctly and choose appropriate archive/refresh windows\n○ DELIVER:\n  • Tool: Power BI Service > Dataset settings > Refresh history > Check duration (incremental refresh should complete faster than previous full refresh baseline)\n  • Metric: Compare refresh duration before/after incremental policy (expect 80-95% time reduction for large tables), verify partition count in XMLA endpoint using SQL Server Management Studio\n  • Validation: Trigger manual refresh > Refresh history shows \"Completed\" < 30 minutes for multi-million row table (vs. hours for full refresh), query data to verify recent rows present\n\n## 40. Query Folding Optimization\n- PREPARE:\n  • Prerequisite: Power Query Editor in Power BI Desktop, data source that supports query folding (SQL Server, Azure SQL DB, Oracle, Teradata - NOT Excel, CSV, SharePoint lists)\n  • Selection: Query folding (push transformations to source database) vs. In-memory transformations in Power Query engine vs. Dataflows for reusable folding logic\n  • Execution: Power BI Desktop > Transform data > Right-click transformation step > View Native Query (if grayed out, step breaks folding)\n• MODEL:\n  • Folding Verification: Right-click any Power Query step > \"View Native Query\" enabled = folding works, grayed out = folding broken at that step\n  • Supported Transformations: Filter rows, Remove columns, Rename columns, Sort, Group By, Merge Queries (joins) - these fold to SQL\n  • Folding-Breaking Operations: Add Custom Column with M functions (e.g., `Text.Upper()`), Table.Buffer(), importing from files (CSV, Excel), Web.Contents with relative paths\n  • Source Query Optimization: Use SQL statement in advanced options `SELECT TOP 1000 * FROM Sales WHERE OrderDate > '2023-01-01'` to push filter to source\n  • Merge vs. Join: Use Merge Queries (Power Query join) on SQL tables = folds to SQL JOIN, mixing SQL + Excel source breaks folding\n  • Column Removal: Remove columns EARLY in query steps (before other transforms) - reduces data volume pulled from source if folding works\n  • Diagnostics: Tools > Session Diagnostics > Start Diagnostics > Perform refresh > Stop Diagnostics > Review \"Data Source Query\" logs to see actual SQL generated\n  • **[Critical Distinction]:** Query folding pushes work to source database (fast, leverages indexes) vs. In-memory transformations pull all data then process locally (slow, memory-intensive)\n  • **[Design Boundary]:** Query folding does NOT work across different data sources (e.g., merging SQL Server table with SharePoint list breaks folding, requires dual data pulls)\n  • **[Exam Focus]:** PL-300 Objective 1.3 - \"Optimize performance of queries and data models\" tests ability to identify folding-breaking steps and optimize query design\n○ DELIVER:\n  • Tool: Power Query Editor > View tab > Query Dependencies (shows data lineage) and Formula Bar (check for folding-friendly M code)\n  • Metric: Refresh duration with folding vs. without (run Diagnostics twice to compare), actual rows processed in source vs. loaded into model\n  • Validation: Tools > Session Diagnostics > Review diagnostic logs > Verify \"Data Source Query\" section contains SQL SELECT statements (proves folding occurred), check duration of \"Evaluate Partition\" steps < 10 seconds per partition\n```\n\n```\n## 41. Performance Analyzer Tool\n- PREPARE:\n  • Prerequisite: Power BI Desktop with open .pbix file containing report visuals to profile\n  • Selection: View tab > Performance Analyzer (launches profiler), Start recording (begins capture), or Clear (resets collected data)\n  • Execution: View > Performance Analyzer > Start Recording, interact with report visuals (filters, slicers, page navigation), then Stop Recording to capture query durations\n• MODEL:\n  • Visual Query Duration: Measures time for DAX query execution (target < 100-500ms for interactive performance)\n  • DAX Query Panel: Displays exact DAX queries generated by each visual, copy to DAX Studio for optimization analysis\n  • Direct Query Mode Impact: Shows longer durations (1-5 seconds typical) when querying remote data sources vs. Import mode cached data\n  • **[Critical Distinction]:** Performance Analyzer captures **client-side rendering time** (visual display + query execution) while DAX Studio measures **server-side query execution only** (excludes rendering overhead)\n  • **[Design Boundary]:** Performance Analyzer cannot profile Power Query refresh operations (M transformations), only DAX queries from visuals—use Query Diagnostics for M performance issues\n  • **[Exam Focus]:** Skill \"Optimize performance\" includes interpreting Performance Analyzer results to identify slow visuals (long query durations) and reducing complexity of DAX measures with CALCULATE/FILTER modifications\n  • Copy Queries Button: Exports DAX queries to clipboard for pasting into DAX Studio or external optimization tools\n  • Export to JSON: Saves performance trace data as .json file for documentation or comparison across report versions\n○ DELIVER:\n  • Tool: Performance Analyzer pane in Power BI Desktop, shows Duration (ms) column for each visual's query execution time\n  • Metric: Visual query duration < 500ms (acceptable), 500-2000ms (needs optimization), > 2000ms (critical performance issue requiring DAX refactoring)\n  • Validation: Compare \"DAX query\" duration vs. \"Visual display\" duration—high visual display time suggests complex custom visuals or overloaded canvas, not DAX issues\n\n## 42. DAX Studio for Query Optimization\n- PREPARE:\n  • Prerequisite: Download DAX Studio (free external tool from daxstudio.org), requires .NET Framework 4.7.2+, connects to Power BI Desktop or Power BI Service Analysis Services engine\n  • Selection: Connect to Power BI Desktop (localhost:port from Performance Analyzer), Azure Analysis Services (server URL), or SQL Server Analysis Services (SSAS tabular instance)\n  • Execution: Launch DAX Studio > Connect to > Active Power BI/SSAS Tabular Instance, paste DAX query from Performance Analyzer, press F5 to execute and view Server Timings\n• MODEL:\n  • Server Timings Tab: Shows Storage Engine (SE) duration (data retrieval from compressed VertiPaq columnar store) and Formula Engine (FE) duration (DAX calculations/context transitions)\n  • Query Plan Analysis: Displays VertiPaq scan operators, cache hits, and cardinality estimates—high FE/SE ratio (> 50%) indicates inefficient DAX requiring CALCULATE/FILTER refactoring\n  • VertiPaq Analyzer: Integrated tool showing table/column sizes in memory, cardinality, compression ratios—identifies large dictionaries consuming RAM (> 1GB per column suggests denormalization issues)\n  • **[Critical Distinction]:** DAX Studio measures **Storage Engine time** (compressed column scan operations) separately from **Formula Engine time** (row-by-row iteration overhead), while Performance Analyzer shows combined total duration only\n  • **[Design Boundary]:** DAX Studio connects to local Power BI Desktop via Analysis Services localhost port (dynamic port assigned at startup)—connection fails if Desktop not running or .pbix file closed\n  • **[Exam Focus]:** Skill \"Optimize model performance\" includes using DAX Studio Server Timings to identify context transition issues (CALCULATE creating row context) and replacing iterators like SUMX with simpler aggregations like SUM()\n  • Metrics Tab: Shows total memory usage (MB), table row counts, and relationship cardinalities—helps diagnose bloated models exceeding Premium capacity SKU limits (P1 = 25GB, P2 = 50GB compressed)\n  • Benchmark Feature: Executes DAX queries multiple times with cold/warm cache scenarios to measure average query performance under production conditions\n○ DELIVER:\n  • Tool: DAX Studio Server Timings pane, displays SE Duration (ms) and FE Duration (ms) with color-coded bars showing relative overhead\n  • Metric: FE/SE ratio < 0.3 (optimal), 0.3-1.0 (acceptable), > 1.0 (critical inefficiency—Formula Engine dominating execution, likely row-by-row iteration in FILTER/CALCULATE)\n  • Validation: Compare VertiPaq Analyzer dictionary sizes—columns > 500MB uncompressed suggest high cardinality text fields needing normalization into dimension tables with integer keys\n\n## 43. Lineage View and Impact Analysis\n- PREPARE:\n  • Prerequisite: Power BI Service workspace with published dataset (.pbix or Power BI Dataset), requires Viewer role or higher to access lineage diagram\n  • Selection: Workspace > Dataset settings > Lineage view (shows upstream data sources and downstream reports/dashboards), or specific report > Related content > Lineage\n  • Execution: Navigate to Power BI Service workspace, select dataset from list, click ellipsis (...) > Lineage view to display interactive dependency graph\n• MODEL:\n  • Upstream Dependencies: Shows connected data sources (SQL Database, SharePoint list, Excel file from OneDrive) with refresh status indicators (green = success, red = failure)\n  • Downstream Impact: Displays all reports, dashboards, and paginated reports consuming the dataset—identifies reports at risk when dataset schema changes (renamed measures/columns)\n  • Dataflow Integration: Lineage view includes Power BI Dataflows (cloud-based Power Query transformations) as intermediate nodes between raw sources and datasets\n  • **[Critical Distinction]:** Lineage view shows **logical data flow relationships** (which reports use which datasets) while Data Source Settings shows **credential-level connections** (authentication details for each source)\n  • **[Design Boundary]:** Lineage view only traces dependencies within the same Power BI tenant—cannot show external BI tools (Tableau, Excel) connected via XMLA endpoint or Analyze in Excel feature\n  • **[Exam Focus]:** Skill \"Manage datasets\" includes using Lineage view to assess impact of breaking changes (deleting dataset field breaks 12 downstream reports) before modifying shared dataset schema\n  • Dataset Chain Visualization: Shows dataset-to-dataset relationships when using \"Connect to Power BI dataset\" feature to build composite models (live connection + additional tables)\n  • Refresh Propagation: Lineage diagram indicates scheduled refresh times—cascading refreshes from dataflow (6 AM) to dataset (7 AM) to dependent datasets (8 AM) avoid stale data\n○ DELIVER:\n  • Tool: Power BI Service Lineage view UI, displays node graph with color-coded connections (blue = active, gray = unused, red = broken)\n  • Metric: Count of downstream dependent objects (reports, dashboards) per dataset—high count (> 20 reports) suggests shared enterprise dataset requiring careful change management process\n  • Validation: Click dataset node to verify \"Refresh history\" shows successful refreshes—failed upstream refreshes cascade errors to all downstream reports sharing the dataset\n\n## 44. Sensitivity Labels and Data Protection\n- PREPARE:\n  • Prerequisite: Microsoft Purview Information Protection enabled in tenant (requires E5 or Compliance Add-on license), sensitivity labels configured by compliance admin in Microsoft Purview compliance portal\n  • Selection: Power BI Desktop > File > Info > Sensitivity label dropdown (Confidential, Highly Confidential, Public), or Power BI Service > Dataset settings > Sensitivity section\n  • Execution: In Power BI Desktop, select File > Info > Apply sensitivity label > Choose \"Confidential\" from dropdown, publish to Service to enforce label policy\n• MODEL:\n  • Label Inheritance: Sensitivity labels applied to dataset automatically flow to downstream reports and dashboards—\"Highly Confidential\" dataset forces all dependent reports to same classification\n  • Export Restrictions: Labels with \"Do not forward\" or \"Encrypt\" protection prevent Export to Excel/PowerPoint options from appearing in report menus for unauthorized users\n  • Audit Logging: Microsoft Purview tracks sensitivity label changes—admin reviews compliance reports showing \"User X downgraded label from Confidential to Public\" events\n  • **[Critical Distinction]:** Sensitivity labels provide **file-level encryption and access restrictions** enforced by Microsoft Purview, while Row-Level Security provides **data-level filtering** based on DAX rules within the report\n  • **[Design Boundary]:** Sensitivity labels require Power BI Premium capacity or Premium Per User (PPU) license to enforce downstream inheritance—Pro licenses only support manual labeling without automatic propagation\n  • **[Exam Focus]:** Skill \"Manage datasets\" includes applying appropriate sensitivity labels to datasets containing PII (Personally Identifiable Information) like email addresses or SSNs, preventing unauthorized exports\n  • Mandatory Labeling Policy: Admin can require all .pbix files to have sensitivity label before publishing—prevents unlabeled reports from reaching Power BI Service workspace\n  • Label-Based Conditional Access: Integration with Azure AD Conditional Access policies blocks report access from unmanaged devices when dataset labeled \"Highly Confidential\" (requires compliant/corporate devices only)\n○ DELIVER:\n  • Tool: Power BI Service > Admin portal > Audit logs, filter by Activity = \"Changed sensitivity label\" to track compliance violations\n  • Metric: Percentage of datasets with sensitivity labels applied (target 100% for regulated industries like healthcare HIPAA or finance SOX compliance)\n  • Validation: Attempt Export to Excel from report with \"Confidential - Encrypt\" label—verify export button disabled/grayed out for users without decryption rights in Purview policy\n\n## 45. Usage Metrics and Report Analytics\n- PREPARE:\n  • Prerequisite: Power BI Service workspace with published report, usage metrics available after 24-48 hours of report activity, requires dataset owner or workspace admin role\n  • Selection: Power BI Service > Report > Ellipsis (...) > View usage metrics report (opens auto-generated .pbix analyzing views/users/shares), or Settings > Usage metrics > Enable per-user data\n  • Execution: Navigate to report in Power BI Service, click ellipsis (...) menu, select \"View usage metrics report\" to launch pre-built analytics dashboard\n• MODEL:\n  • Views Per Day Metric: Line chart showing daily report opens—spike detection identifies popular reports (> 500 views/day) vs. unused reports (< 10 views/month candidates for archival)\n  • Unique Viewers Count: Distinct user count accessing report—low adoption (< 5% of workspace members) suggests poor discoverability or irrelevant content requiring stakeholder feedback\n  • Platform Distribution: Breakdown of views by Power BI Service web browser (60%), Power BI Mobile app (25%), embedded iframe in Teams/SharePoint (15%)—mobile percentage indicates field worker usage\n  • **[Critical Distinction]:** Usage Metrics reports show **content consumption patterns** (who views which pages) while Performance Analyzer shows **query execution performance** (how long visuals take to render)\n  • **[Design Boundary]:** Usage metrics data retained for 90 days only—export to Excel or create separate dataset snapshot for long-term trend analysis beyond 3-month rolling window\n  • **[Exam Focus]:** Skill \"Deploy and manage assets\" includes analyzing usage metrics to identify underutilized reports (candidates for decommissioning) and high-traffic reports requiring Premium capacity migration\n  • Per-User Data Toggle: Enable \"Usage Metrics v2\" in tenant settings to see individual user names—disabled by default for privacy, shows aggregated counts only without PII\n  • Distribution Methods Metric: Tracks report access via direct link (40%), app (35%), workspace browse (15%), email subscription (10%)—high subscription percentage indicates push-based consumption model\n○ DELIVER:\n  • Tool: Auto-generated Usage Metrics report in Power BI Service, contains 5 pre-built pages: Report usage, Report performance, Users, Distribution methods, Platform details\n  • Metric: Report abandonment rate = (unique viewers who opened report but spent < 10 seconds) / (total unique viewers)—high rate (> 50%) suggests misleading report title or broken landing page\n  • Validation: Cross-reference usage metrics \"Unique viewers\" count with Azure AD group membership—if report shared to 200-person distribution group but only 15 viewers, reassess target audience\n\n## 46. Alerts and Subscriptions\n- PREPARE:\n  • Prerequisite: Power BI Service workspace with published dashboard (subscriptions require report or dashboard, not dataset alone), requires Edit permissions on content to create subscriptions\n  • Selection: Dashboard tile with numeric KPI visual > Ellipsis (...) > Manage alerts (set threshold on card/gauge/KPI visual), or Report > Subscribe > Email subscription (sends snapshot on schedule)\n  • Execution: Navigate to dashboard in Power BI Service, select KPI tile showing \"Total Sales\", click ellipsis > Manage alerts > Add alert rule > Set threshold \"Total Sales above 1000000\"\n• MODEL:\n  • Data-Driven Alerts: Threshold-based notifications on dashboard tiles—\"Revenue < 500000\" triggers email when condition met during scheduled dataset refresh (maximum 24-hour check frequency)\n  • Alert Frequency Limit: Maximum 1 alert evaluation per hour per tile—high-frequency monitoring (every 5 minutes) not supported, use Power Automate flow with Power BI connector for real-time alerting\n  • Email Subscription Scheduling: Send report snapshot daily at 8 AM, weekly on Monday, or monthly on 1st day—includes embedded thumbnail image and hyperlink to live report\n  • **[Critical Distinction]:** Data alerts trigger **condition-based notifications** on dashboard tiles only (not reports), while email subscriptions send **scheduled snapshots** of full report pages regardless of data values\n  • **[Design Boundary]:** Alerts limited to dashboard tiles containing card, gauge, or KPI visuals—cannot set alerts on table visuals, maps, or slicer controls (unsupported visual types)\n  • **[Exam Focus]:** Skill \"Deploy and manage assets\" includes configuring email subscriptions to deliver daily report snapshots to stakeholder distribution lists, enabling self-service consumption without login\n  • Subscription Attachment Options: Include report as PDF attachment (max 25MB), PowerPoint slides (one slide per page), or link-only (reduces email size, requires recipients to have workspace access)\n  • Failed Subscription Handling: Service automatically disables subscription after 3 consecutive failures (broken data source, deleted report)—admin receives notification to fix underlying issue\n○ DELIVER:\n  • Tool: Power BI Service > Dashboard tile > Manage alerts UI, shows active alerts with threshold values and last triggered timestamp\n  • Metric: Alert response time = time between dataset refresh completion and email notification delivery (typically 5-15 minutes)—delays suggest email throttling or tenant performance issues\n  • Validation: Create test alert \"Sales > 0\" (always true condition), trigger dataset refresh, verify email notification received within 15 minutes at specified recipient inbox\n\n## 47. Export Options (PDF, PowerPoint, Excel)\n- PREPARE:\n  • Prerequisite: Published report in Power BI Service, export permissions enabled in tenant admin settings (Export to PDF, Export to PowerPoint, Analyze in Excel)\n  • Selection: Report > Export dropdown (PDF, PowerPoint, Excel with report visuals, or Analyze in Excel with live connection), or Visual ellipsis (...) > Export data (CSV from specific visual)\n  • Execution: Open report in Power BI Service, click File > Export to PDF > Select \"Current page only\" or \"All pages\", adjust page size to Letter/A4, download generated .pdf file\n• MODEL:\n  • PDF Export Layout: Maintains report page dimensions (16:9, 4:3, custom) and visual positioning—exported PDF matches browser rendering with filters applied at export time (not live data)\n  • PowerPoint Export Format: Creates .pptx with one slide per report page, embeds static images (not live visuals)—useful for offline presentations, file size 5-20MB depending on visual complexity\n  • Analyze in Excel Feature: Generates .odc (Office Data Connection) file connecting Excel PivotTable to Power BI dataset via XMLA endpoint—enables live queries with Excel's familiar PivotTable interface\n  • **[Critical Distinction]:** \"Export data\" from visual context menu extracts **underlying data rows** (up to 150,000 rows to .csv), while \"Analyze in Excel\" creates **live connection to dataset** allowing PivotTable analysis without data duplication\n  • **[Design Boundary]:** PDF/PowerPoint exports are static snapshots—no interactive slicers or drill-through functionality preserved (users cannot filter exported PDF, unlike live report)\n  • **[Exam Focus]:** Skill \"Deploy and manage assets\" includes configuring export settings for stakeholders—disable Excel export to prevent data exfiltration, enable PDF for board presentations requiring offline access\n  • Export Data Limitations: Underlying data export limited to 30,000 rows for non-Premium workspaces, 150,000 rows for Premium—tables with > 150K rows require alternate export (Power BI Paginated Reports or Dataflows)\n  • PowerPoint Live Tile: Insert > Power BI option in PowerPoint adds live-updating report tile (requires internet connection)—alternative to static export for presentations needing current data\n○ DELIVER:\n  • Tool: Power BI Service > Report > File > Export menu, shows enabled options based on admin tenant settings and user permissions\n  • Metric: PDF file size < 25MB (email attachment limit), PowerPoint slides < 50MB—exceeding limits suggests too many pages/visuals, split report into multiple files\n  • Validation: Open exported PDF, verify current filter context preserved (if \"Region = West\" selected before export, PDF shows West data only, not all regions)\n\n## 48. Embed Reports in Teams/SharePoint\n- PREPARE:\n  • Prerequisite: Microsoft Teams desktop/web app or SharePoint Online site, Power BI Service workspace with published report, users require Power BI Pro/Premium or PPU license to view embedded content\n  • Selection: Teams channel > Add tab > Power BI (embeds report as tab), SharePoint page > Edit > Insert > Power BI web part (embeds report in page), or Share > Embed in SharePoint Online\n  • Execution: In Teams channel, click + to add tab, select Power BI from app gallery, choose workspace and report, name tab \"Sales Dashboard\", save to embed report in channel tab\n• MODEL:\n  • Teams Tab Integration: Report embedded as full Teams tab—preserves interactivity (slicers, filters, drill-through) and respects Power BI Row-Level Security based on Teams user identity\n  • SharePoint Web Part: Power BI web part on SharePoint page allows selecting specific report page—single page embedded, users click \"Go to report\" link to open full report in Service\n  • Automatic Context Passing: Teams personal app shows personalized report views—if user belongs to \"Sales\" Azure AD group, embedded report filters to Sales data via RLS without manual configuration\n  • **[Critical Distinction]:** Teams tab embeds **interactive Power BI report** with full functionality (users can change filters/slicers), while email subscription sends **static image snapshot** without interactivity\n  • **[Design Boundary]:** Embedded reports in Teams/SharePoint require users to have underlying workspace access (Viewer role minimum)—guest users (external domain) need Power BI guest user access enabled in tenant\n  • **[Exam Focus]:** Skill \"Deploy and manage assets\" includes embedding reports in Teams channels for departmental consumption—leverages existing collaboration hub, reduces need for separate Power BI workspace logins\n  • Link Sharing vs. Embed: \"Share\" > \"Link to this report\" generates URL—paste in Teams chat for quick access, but opens report in browser/app, not embedded in-place tab\n  • Mobile Teams App: Embedded Power BI reports render in Teams mobile app with touch-optimized navigation—users access reports on iOS/Android without separate Power BI mobile app install\n○ DELIVER:\n  • Tool: Microsoft Teams > Channel > Power BI tab, displays live report with refresh timestamp showing last dataset update (e.g., \"Data refreshed 2 hours ago\")\n  • Metric: Embedded report load time < 5 seconds in Teams desktop app—delays suggest network latency, overly complex report (> 50 visuals per page), or under-provisioned Premium capacity\n  • Validation: Access Teams channel as different user with RLS restrictions—verify embedded report shows filtered data per user identity (sales rep sees own region only, manager sees all regions)\n\n## 49. Goals and Metrics Feature\n- PREPARE:\n  • Prerequisite: Power BI Premium capacity or Premium Per User license (Goals feature not available in Pro workspaces), workspace admin creates goals and assigns owners\n  • Selection: Power BI Service > Workspace > New > Metrics hub (centralized goal tracking), create Goal (e.g., \"Increase Revenue to $5M by Q4\"), connect to dataset measure or manual entry\n  • Execution: Navigate to Premium workspace, click New > Metrics, create goal \"Customer Satisfaction Score > 85%\", connect to dataset measure [Average CSAT Score], set target value and deadline\n• MODEL:\n  • Automated Data Connection: Link goal to Power BI dataset measure—goal progress automatically updates when dataset refreshes (e.g., \"Revenue YTD\" measure feeds \"Annual Revenue Goal\" with real-time progress)\n  • Manual Check-in Updates: For goals without dataset connections (operational KPIs like \"Hire 10 engineers by June\"), owners manually log progress values and status notes (On Track, At Risk, Behind)\n  • Subgoals Hierarchy: Break high-level goal \"Improve NPS to 75\" into subgoals \"Reduce response time < 2 hours\" (support team), \"Launch 3 new features\" (product team)—roll-up progress automatically\n  • **[Critical Distinction]:** Goals feature tracks **long-term strategic objectives** with target deadlines (quarters/years), while dashboard KPI visuals show **current operational metrics** without target comparisons or progress tracking\n  • **[Design Boundary]:** Goals feature requires Premium capacity—attempting to create goal in Pro workspace shows \"Upgrade to Premium\" prompt, cannot use free shared capacity for metrics hub\n  • **[Exam Focus]:** Skill \"Deploy and manage assets\" includes configuring Goals connected to dataset measures for automated progress tracking—reduces manual status reporting overhead for executives\n  • Status Rules: Goals automatically calculated as \"On Track\" (current value ≥ 90% of pro-rated target), \"At Risk\" (70-90%), \"Behind\" (< 70%)—color-coded visual indicators for leadership dashboards\n  • Scorecard View: Metrics hub displays all workspace goals in scorecard format—one-page executive summary showing 10-20 strategic metrics with progress bars and owners\n○ DELIVER:\n  • Tool: Power BI Service > Metrics hub page, displays goal progress visualization (line chart showing actual vs. target over time)\n  • Metric: Goal attainment percentage = (current value / target value) × 100—values ≥ 100% indicate goal achieved, < 80% suggests intervention needed\n  • Validation: Trigger dataset refresh connected to goal—verify goal progress updates within 15 minutes showing new current value (e.g., \"Revenue\" goal updates from $3.2M to $3.5M after refresh)\n\n## 50. Copilot for Power BI Natural Language Queries\n- PREPARE:\n  • Prerequisite: Power BI Service with Copilot enabled in tenant admin settings (Fabric F64+ capacity required), dataset must have well-defined relationships and measures for accurate NLQ responses\n  • Selection: Report reading view > Copilot pane (right side), type natural language question \"Show total sales by region\" or \"Which product has highest profit margin\", Copilot generates DAX query and visual\n  • Execution: Open report in Power BI Service, click Copilot icon (brain/sparkle symbol) in top toolbar, type question \"What were top 5 customers by revenue last quarter\", press Enter to generate answer\n• MODEL:\n  • Semantic Model Optimization: Copilot accuracy improves when tables/columns have synonyms configured (Revenue = Sales = Income)—add synonyms in Power BI Desktop modeling view for better NLQ understanding\n  • DAX Measure Generation: Copilot creates temporary DAX measures for complex queries—\"Show revenue growth rate year-over-year\" generates CALCULATE with SAMEPERIODLASTYEAR function automatically\n  • Suggested Questions: Copilot displays 3-5 starter questions based on dataset structure—\"What is total sales?\", \"Show trends over time\", \"Compare categories\"—helps users discover insights without BI expertise\n  • **[Critical Distinction]:** Copilot generates **dynamic visuals and DAX queries** from natural language, while Q&A visual (legacy feature) creates **single visual only** with more limited NLQ capabilities (no multi-step reasoning)\n  • **[Design Boundary]:** Copilot requires Fabric capacity (F64 minimum, $8,000+/month)—not available in Power BI Premium P1-P3 SKUs or Premium Per User licenses, limiting accessibility for smaller organizations\n  • **[Exam Focus]:** Skill \"Deploy and manage assets\" includes configuring dataset metadata (synonyms, descriptions) to improve Copilot accuracy—well-documented semantic model enables non-technical users to self-serve insights\n  • Summarization Feature: Copilot generates natural language summary of report page—\"Sales increased 15% vs. last year, driven by West region growth of 23%\"—useful for executive briefings\n  • Narrative Visual Integration: Right-click visual > \"Explain this visual\" sends chart data to Copilot for automatic insight generation—identifies outliers, trends, anomalies with plain-text explanations\n○ DELIVER:\n  • Tool: Power BI Service Copilot pane, displays generated visuals, DAX queries (expandable code view), and natural language summary of results\n  • Metric: Copilot accuracy rate = (correct responses / total queries) × 100—measure by user feedback thumbs up/down—target > 80% accuracy for well-modeled datasets with synonyms configured\n  • Validation: Ask Copilot ambiguous question \"Show sales\"—verify response requests clarification (\"Do you mean Total Sales or Sales Quantity?\") rather than generating incorrect visual, indicating robust semantic understanding\n```\n\n\n\n## STEP 4: VISUAL MENTAL ANCHORS\n\n### Mental Anchor 1: The Data Factory Assembly Line\n\n**The Physical Scene:** Picture an industrial factory with three distinct zones. At the loading dock (PREPARE zone), raw materials arrive on different trucks—some containers hold clean parts, others are full of tangled, dusty components. The materials pass through a cleaning and sorting station with conveyor belts, inspection gates, and quality control checkpoints. In the middle zone (MODEL), workers arrange cleaned parts on workbenches in organized patterns, connecting pieces with labeled wires and joints, creating functional assemblies. The final zone (DELIVER) is a showroom floor where finished products sit on rotating displays with interactive touchscreens, allowing visitors to explore features from different angles.\n\n**Concept Mapping:**\n- **Loading Dock Trucks** = Data Source Connectivity and Storage Modes (Import trucks bring full loads and park; DirectQuery trucks maintain a live connection back to the warehouse; Live Connection trucks are direct pipelines)\n- **Cleaning Station Conveyor** = Power Query Editor and M Language (each transformation step is a station on the belt; Query Folding means the supplier pre-cleans before shipping, making your belt run faster)\n- **Assembly Workbenches** = Star Schema Design and Relationships (the central bench is your fact table; surrounding workstations are dimension tables connected by labeled wires representing cardinality)\n- **Showroom Displays** = Reports and Dashboards (rotating displays are slicers changing perspectives; touchscreens are drill-through actions; security badges control which displays each visitor can access)\n\n**Why It Helps:** This factory metaphor reinforces that data analysis is a sequential manufacturing process—you can't display what you haven't assembled, and you can't assemble what you haven't cleaned. When you encounter issues, you immediately know which \"factory zone\" to inspect. The physical flow from messy to organized to presentable matches your actual workflow, making it natural to remember that transformation happens before modeling, and modeling happens before visualization. The assembly line structure prevents the common mistake of trying to \"fix\" data problems with complex DAX when the real solution is better Power Query cleaning upstream.\n\n---\n\n### Mental Anchor 2: The Smart Building with Living Blueprints\n\n**The Physical Scene:** Envision a modern skyscraper where the walls are made of transparent smart glass displaying live data. The building's foundation contains a massive vault (dataset storage) with different sections: some rooms hold complete archived file cabinets (Import mode), while others have windows showing live feeds from external buildings (DirectQuery). On each floor, different departments use calculation rooms equipped with whiteboards covered in formulas—some whiteboards compute once and store the result (calculated columns), while others recalculate every time someone looks at them (measures). The building's security system uses facial recognition (RLS) and room access cards (OLS) to control what each person sees. Elevators represent time intelligence, allowing people to travel to different time periods to compare monthly, quarterly, or yearly views.\n\n**Concept Mapping:**\n- **Building Foundation Vault** = Storage Modes and Composite Models (different room types in the vault represent Import, DirectQuery, and hybrid approaches; reinforced sections are incremental refresh partitions)\n- **Department Calculation Rooms** = DAX Calculated Columns vs Measures (columns are pre-printed posters on the wall, always visible; measures are live video feeds that update based on who's watching and what filters they apply)\n- **Security Recognition Systems** = Row-Level and Object-Level Security (facial recognition checks your identity and filters which rows/floors you see; access cards determine which specific rooms/objects you can enter)\n- **Time-Travel Elevators** = DAX Time Intelligence Functions (buttons like SAMEPERIODLASTYEAR, DATEADD, and TOTALYTD transport you to different time-based floors while maintaining your current view context)\n\n**Why It Helps:** The building metaphor clarifies the fundamental distinction between stored calculations (architectural elements built into the structure) and dynamic calculations (smart displays that change based on context). When students struggle with why a calculated column doesn't respond to slicers but a measure does, they can visualize a static poster versus a dynamic video feed. The security system makes RLS and OLS tangible—it's not abstract permission settings, it's literal barriers controlling movement. The transparent walls emphasize that in Power BI, everything is ultimately about what viewers see through their specific lens, making filter context and row context intuitive concepts rather than abstract technical terms.\n\n---\n\n### Mental Anchor 3: The Expedition Command Center\n\n**The Physical Scene:** Imagine a sophisticated mission control room for multiple exploration teams in the field. Large wall screens display live dashboards tracking team progress, while workstations below run detailed analysis on specific mission aspects. The center has three operational phases: Mission Prep (configuring equipment, testing communication channels, establishing base camps in dev/test/prod locations), Mission Execution (teams streaming data back through satellite gateways, analysts creating visual reports of findings, commanders watching KPIs on centralized displays), and Mission Distribution (packaged briefings distributed to stakeholders, mobile field guides for executives, scheduled update broadcasts). A central lineage map shows how information flows from remote sensors through processing stations to final displays, with impact alerts highlighting when upstream changes affect downstream reports.\n\n**Concept Mapping:**\n- **Base Camp Progression** = Deployment Pipelines and Workspace Management (dev camp for testing, test camp for validation, prod camp for live operations; workspace roles determine who can plan vs execute vs observe missions)\n- **Communication Gateway Network** = Gateway Configuration and Dataflows (satellite dishes connecting remote on-premises sites to cloud command center; dataflows are preprocessing stations that clean and stage data before main analysis)\n- **Command Center Wall Screens** = Dashboards and Apps (pinned tiles are mission-critical KPIs requiring constant monitoring; Q&A natural language is like asking the AI assistant for instant intel; alerts are automated warning systems)\n- **Stakeholder Briefing Packages** = Distribution and Embedding Options (paginated reports are formal briefing documents; Teams/SharePoint embedding places live screens in field offices; export options create portable briefing folders)\n\n**Why It Helps:** The expedition metaphor captures the collaborative, multi-stage nature of enterprise Power BI deployment. It normalizes the complexity—of course you need multiple base camps and rigorous testing before a real expedition; of course you need robust communication infrastructure for remote data sources. The command center structure helps students understand the distinction between workspaces (operational zones), datasets (mission data streams), reports (analytical views), and dashboards (executive summaries). When troubleshooting performance issues, the visual of data traveling through gateways and processing stations makes it obvious where bottlenecks occur. The lineage map and impact analysis become navigation charts showing how changing one element affects dependent systems, preventing the common mistake of modifying a dataset without realizing it breaks downstream reports.\n\n---\n\n## STEP 5: WORKED EXAMPLE\n\n### Student Question:\n\"I've created a sales report with a revenue measure that works perfectly when sliced by Product Category, but when my manager applies the Year slicer, the total revenue doesn't change at all—it just shows the same number for every year. When she filters to 2023, it still displays the complete revenue from all years. I've checked my Date table relationships and they look correct. The line chart showing revenue over time works fine, but this measure in the card visual is stuck. What am I missing?\"\n\n### Chart Navigation:\nThis scenario signals issues in the **MODEL** phase, specifically around relationships and DAX context. The student should consult:\n\n1. **Table Relationships and Cardinality** (MODEL phase) - First verify the relationship configuration\n2. **DAX Filter Context and Row Context** (MODEL phase) - The symptom suggests filter context isn't propagating\n3. **DAX Measures and Implicit Measures** (MODEL phase) - Check if the measure formula respects filter context\n4. **Star Schema Design** (MODEL phase) - Confirm the Date table is properly configured as a dimension\n5. **Data Categorization and Hierarchies** (MODEL phase) - Ensure the Date table is marked as a Date table\n\nThe fact that Product Category slicing works but Date slicing doesn't immediately points to a relationship issue with the Date table specifically, not a fundamental DAX problem.\n\n### The Diagnosis:\nFollowing the lifecycle chart reveals a classic \"broken bridge\" in the MODEL phase. Using the **Smart Building metaphor**, this is like having department calculation rooms (measures) that can't see through certain smart glass walls (relationships) to filter their view. The measure itself is probably correct (it works with Product Category), but the \"elevator system\" (Date table relationship) isn't transporting the time-based filter context properly.\n\nThe chart's MODEL phase checklist reveals the most likely culprits:\n- **Relationship Issue**: The Date table may not have an active relationship to the Sales fact table, or the relationship exists but is using the wrong columns (joining on Date strings instead of proper Date values)\n- **Date Table Configuration**: The Date table might not be marked as a Date table in Power BI, causing time intelligence and filter propagation failures\n- **Inactive Relationship**: Multiple date columns in the Sales table (OrderDate, ShipDate, DueDate) might have created multiple relationships, with the intended one set to inactive\n- **DAX Filter Context**: Less likely here, but the measure could be using CALCULATE with ALL(Date) or similar functions that remove filter context\n\n### The Solution:\n\n**Immediate Diagnostic Actions:**\n1. **Verify Relationship Status**: Open Model view and check the connection line between Date table and Sales table—a solid line indicates active, dotted indicates inactive\n2. **Inspect Relationship Configuration**: Right-click the relationship line and examine cardinality (should be One-to-Many from Date to Sales) and cross-filter direction (should be Single, from Date to Sales)\n3. **Check Date Table Marking**: Select the Date table, go to Table tools > Mark as date table, and verify it's properly configured with a unique date column\n4. **Review Measure Formula**: Open DAX formula for the revenue measure and confirm it doesn't contain ALL(), ALLSELECTED(), or REMOVEFILTERS() functions that would ignore the Date filter\n\n**Concrete Fixes:**\n- **If relationship is inactive**: Right-click the relationship line and select \"Make this relationship active\" (you may need to make another relationship inactive first)\n- **If no relationship exists**: Create one by dragging the Date column from Date table to OrderDate (or appropriate date field) in Sales table\n- **If Date table isn't marked**: Table tools > Mark as date table > Select the Date column as the unique identifier\n- **If multiple relationships exist**: Use USERELATIONSHIP() function in the measure to specify which date relationship to activate: `Total Revenue = CALCULATE(SUM(Sales[Revenue]), USERELATIONSHIP(Sales[OrderDate], Date[Date]))`\n\n**Validation Steps:**\n1. Create a matrix visual with Date[Year] on rows and the revenue measure as values—it should now show different amounts per year\n2. Add Product Category as a second row level—both dimensions should filter the measure correctly\n3. Test the Performance Analyzer to confirm the DAX query includes the Date table in its filter context\n\n### Learning Point:\nThe lifecycle structure prevented wild goose chasing. Instead of immediately rewriting DAX formulas (a DELIVER phase cosmetic fix) or re-importing data (a PREPARE phase nuclear option), the student followed the chart's logical flow: visuals display what the model provides, so visual problems usually stem from model configuration. The **MODEL** phase checklist systematically addresses the three pillars of correct calculations: proper schema structure (relationships), correct storage design (Date table configuration), and accurate formulas (DAX context).\n\nThe **Data Factory metaphor** clarifies why the fix worked: the assembly workbenches (star schema) needed properly labeled connecting wires (relationships) for the workstations (tables) to communicate. No amount of adjusting the showroom displays (report visuals) would fix disconnected workbenches.\n\nThis structured approach demonstrates that the PL-300 lifecycle isn't just organizational theory—it's a practical troubleshooting framework. When a visual misbehaves, trace backward through the lifecycle: DELIVER issues usually have MODEL roots, and MODEL issues sometimes trace back to PREPARE phase data quality. The student now has a reusable mental pattern: strange filtering behavior → check relationships → verify table configurations → then consider DAX logic, following the factory flow from foundation to finish.\n\n---\n\n## STEP 7: LEARNING PATH SEQUENCE\n\n### Stage 1: Data Foundation Builder\n**\"Establishing the Connection and Transformation Pipeline\"**\n\n**Concepts Included:**\n- Power BI Desktop Environment and Workspace Management\n- Data Source Connectivity (files, databases, web services, APIs)\n- Import vs DirectQuery vs Live Connection Storage Modes\n- Power Query Editor interface and M Language fundamentals\n- Data Transformation and Cleaning techniques\n- Query Folding Optimization principles\n- Data Refresh Configuration basics\n\n**Capabilities Gained:**\nAfter completing this stage, you can independently connect Power BI to diverse data sources, evaluate which storage mode optimally balances freshness and performance for specific scenarios, and build efficient transformation pipelines that clean and shape raw data into analysis-ready tables. You understand how to leverage query folding to push transformations back to source systems, reducing local processing overhead. You've mastered the PREPARE phase lifecycle, enabling you to troubleshoot connection issues, diagnose refresh failures, and optimize data ingestion performance. This foundation unlocks the ability to work confidently with organizational data sources and prepare reliable datasets for modeling.\n\n---\n\n### Stage 2: Model Architect\n**\"Designing Relationships and Calculation Logic\"**\n\n**Concepts Included:**\n- Star Schema Design principles (fact and dimension tables)\n- Table Relationships, Cardinality, and Cross-Filter Direction\n- Data Categorization, Hierarchies, and Date table configuration\n- Composite Models and Hybrid Tables\n- DAX Calculated Columns vs Measures distinction\n- DAX fundamental functions (SUM, AVERAGE, COUNT, DIVIDE)\n- DAX Filter Context and Row Context mechanics\n- DAX Variables for performance and readability\n\n**Capabilities Gained:**\nAfter this stage, you can architect robust data models following star schema best practices, establishing relationships that enable accurate cross-table analysis while maintaining performance. You understand when calculated columns store results at the row level versus when measures dynamically compute based on visual context. You write clean DAX formulas using variables for maintainability and can explain why measures respond to slicers while calculated columns don't. This MODEL phase mastery enables you to build self-service models where business users can slice, dice, and analyze data without creating calculation errors. You've unlocked the ability to design scalable models that grow with organizational complexity while maintaining accuracy and performance.\n\n---\n\n### Stage 3: Advanced Calculation Designer\n**\"Implementing Complex Analytics and Intelligence\"**\n\n**Concepts Included:**\n- DAX Iterator Functions (SUMX, AVERAGEX, RANKX, FILTER)\n- DAX Time Intelligence Functions (SAMEPERIODLASTYEAR, TOTALYTD, DATEADD)\n- DAX advanced filter functions (CALCULATE, ALL, ALLSELECTED, REMOVEFILTERS)\n- DAX relationship functions (RELATED, RELATEDTABLE, USERELATIONSHIP)\n- Incremental Refresh Policy configuration\n- Performance Analyzer Tool usage\n- DAX Studio for query optimization\n- Composite model advanced scenarios\n\n**Capabilities Gained:**\nAfter completing this stage, you can implement sophisticated analytics that answer complex business questions: year-over-year comparisons, moving averages, cumulative totals, and context-aware calculations that adapt based on user selections. You master iterator functions to perform row-by-row evaluations within filtered contexts, enabling advanced metrics like weighted averages and customer segmentation. You configure incremental refresh to maintain performance on massive datasets by refreshing only changed partitions. You use Performance Analyzer and DAX Studio to diagnose slow queries and optimize calculation logic. This advanced MODEL phase expertise extends your capabilities to enterprise-scale scenarios, enabling you to deliver analytical sophistication that rivals dedicated BI platforms while maintaining self-service accessibility.\n\n---\n\n### Stage 4: Visualization and Interaction Specialist\n**\"Creating Engaging and Intuitive Analytical Experiences\"**\n\n**Concepts Included:**\n- Visual Selection and Use Cases (when to use each chart type)\n- Report Layout and Page Design principles\n- Slicers, Filters, and Cross-Filtering Behavior configuration\n- Drillthrough and Drill-down Navigation patterns\n- Bookmarks and Selection Pane for state management\n- Buttons and Action Configuration for guided analytics\n- Tooltips (Standard and Report Page) for contextual detail\n- Conditional Formatting for visual emphasis\n- Custom Visuals from AppSource\n- Mobile Layout Optimization\n- Accessibility features and best practices\n\n**Capabilities Gained:**\nAfter this stage, you can transform accurate models into compelling visual stories that guide users to insights. You select appropriate visualizations based on data characteristics and analytical goals—knowing when a line chart reveals trends better than a table, or when a scatter plot exposes correlations hidden in bar charts. You design interactive navigation using bookmarks to create \"presentation mode\" experiences or drillthrough pages that reveal detail without cluttering main views. You implement conditional formatting that highlights exceptions, uses buttons to guide analytical workflows, and creates mobile layouts that deliver executive dashboards on any device. This DELIVER phase expertise unlocks your ability to democratize data insights across organizations, creating reports that users intuitively understand and actively engage with rather than ignore.\n\n---\n\n### Stage 5: Enterprise Governance and Distribution Leader\n**\"Securing, Publishing, and Managing Production Solutions\"**\n\n**Concepts Included:**\n- Power BI Service Workspace Management and Workspace Roles\n- Row-Level Security (RLS) and Object-Level Security (OLS) implementation\n- Deployment Pipelines (Development/Test/Production workflows)\n- Dataset Endorsement (Certified/Promoted) for trusted content\n- Gateway Configuration for On-Premises Data connectivity\n- Dataflows for Self-Service ETL and data reuse\n- Dashboard Creation from Reports with tiles and Q&A\n- Power BI Apps for Distribution to business units\n- Sensitivity Labels and Data Protection integration\n- Lineage View and Impact Analysis for change management\n- Usage Metrics and Report Analytics for adoption tracking\n- Alerts, Subscriptions, and automated distribution\n- Embed Reports in Teams/SharePoint for workflow integration\n- Paginated Reports for pixel-perfect formal documents\n- Goals and Metrics Feature for OKR tracking\n- Copilot for Power BI natural language capabilities\n\n**Capabilities Gained:**\nAfter completing this final stage, you can manage the complete lifecycle of enterprise Power BI solutions from development through production deployment and ongoing maintenance. You implement security models that protect sensitive data at the row level while hiding confidential objects entirely from unauthorized users. You establish deployment pipelines that enable safe testing before production release, preventing the common mistake of breaking live reports with untested changes. You configure gateways that securely connect cloud Power BI to on-premises data sources, enabling hybrid analytical architectures. You create dataflows that centralize transformation logic for reuse across multiple datasets, improving consistency and reducing redundancy. You publish curated apps that deliver role-specific analytical experiences, embed live reports in Teams channels where business decisions happen, and configure automated subscriptions that deliver insights proactively. You use lineage view to understand downstream impact before modifying shared datasets, preventing cascading failures. This enterprise expertise extends your capabilities beyond individual report creation to platform leadership, enabling you to architect governed, scalable, and secure analytical ecosystems that serve entire organizations while maintaining compliance, performance, and data quality standards.",
  "pass1Data": {
    "domain": "Business Intelligence & Data Analytics",
    "roleScope": "Power BI Data Analyst",
    "lifecycle": {
      "phase1": "PREPARE",
      "phase2": "MODEL",
      "phase3": "DELIVER"
    },
    "concepts": [
      "Power BI Service Workspace Management",
      "Power BI Desktop Environment",
      "Data Source Connectivity",
      "Power Query Editor (M Language)",
      "Data Transformation and Cleaning",
      "Import vs DirectQuery vs Live Connection Storage Modes",
      "Composite Models and Hybrid Tables",
      "Data Refresh Configuration",
      "Star Schema Design",
      "Table Relationships and Cardinality",
      "DAX Calculated Columns",
      "DAX Measures and Implicit Measures",
      "DAX Iterator Functions (SUMX, AVERAGEX)",
      "DAX Filter Context and Row Context",
      "DAX Time Intelligence Functions",
      "DAX Variables and Query Performance",
      "Row-Level Security (RLS)",
      "Object-Level Security (OLS)",
      "Data Categorization and Hierarchies",
      "Visual Selection and Use Cases",
      "Custom Visuals from AppSource",
      "Report Layout and Page Design",
      "Slicers and Cross-Filtering Behavior",
      "Drillthrough and Drill-down Navigation",
      "Bookmarks and Selection Pane",
      "Buttons and Action Configuration",
      "Tooltips (Standard and Report Page)",
      "Conditional Formatting",
      "Dashboard Creation from Reports",
      "Dashboard Tiles and Q&A",
      "Mobile Layout Optimization",
      "Paginated Reports (SSRS-style)",
      "Power BI Apps for Distribution",
      "Workspace Roles and Permissions",
      "Deployment Pipelines (Dev/Test/Prod)",
      "Dataset Endorsement (Certified/Promoted)",
      "Gateway Configuration for On-Premises Data",
      "Dataflows for Self-Service ETL",
      "Incremental Refresh Policy",
      "Query Folding Optimization",
      "Performance Analyzer Tool",
      "DAX Studio for Query Optimization",
      "Lineage View and Impact Analysis",
      "Sensitivity Labels and Data Protection",
      "Usage Metrics and Report Analytics",
      "Alerts and Subscriptions",
      "Export Options (PDF, PowerPoint, Excel)",
      "Embed Reports in Teams/SharePoint",
      "Goals and Metrics Feature",
      "Copilot for Power BI Natural Language Queries"
    ]
  },
  "validation": {
    "lifecycleConsistency": 98,
    "positiveFraming": 98,
    "formatConsistency": 100,
    "completeness": 100
  },
  "savedLocally": true
}